<system>
<keyword>note</keyword>
	<indexing_tag>description</indexing_tag><symbol>:</symbol> <string>&quot;Eiffel Vision dynamic list. Implementation interface.&quot;</string>
	<indexing_tag>legal</indexing_tag><symbol>:</symbol> <string>&quot;See notice at end of class.&quot;</string>
	<indexing_tag>status</indexing_tag><symbol>:</symbol> <string>&quot;See notice at end of class.&quot;</string>
	<indexing_tag>date</indexing_tag><symbol>:</symbol> <string>&quot;$Date: 2017-05-03 08:56:14 -0700 (Wed, 03 May 2017) $&quot;</string>
	<indexing_tag>revision</indexing_tag><symbol>:</symbol> <string>&quot;$Revision: 100317 $&quot;</string>

<keyword>deferred</keyword> <keyword>class</keyword> 
	<class><location>../implementation_interface/ev_dynamic_list_i.xml</location>EV_DYNAMIC_LIST_I</class> <symbol>[</symbol><generic>G</generic> <symbol>-&gt;</symbol> <class><location>../interface/ev_containable.xml</location>EV_CONTAINABLE</class><symbol>]</symbol>

<keyword>inherit</keyword>
	<class><location>../implementation_interface/ev_any_i.xml</location>EV_ANY_I</class>
		<keyword>redefine</keyword>
			<feature><location>../implementation_interface/ev_dynamic_list_i.xml#f_interface</location>interface</feature>
		<keyword>end</keyword>

<keyword>feature</keyword> <comment>--</comment><comment> Access</comment>

	<anchor>f_interface_item</anchor><feature><location>../implementation_interface/ev_dynamic_list_i.xml#f_interface_item</location>interface_item</feature><symbol>:</symbol> <generic>G</generic>
		<keyword>obsolete</keyword> &quot;Use `item' instead. [2017-05-31]&quot;
			<comment>--</comment><comment> Current item but guaranteed attached for calling from interface only</comment>
		<keyword>require</keyword>
			<tag>readable</tag><symbol>:</symbol> <feature><location>../implementation_interface/ev_dynamic_list_i.xml#f_index</location>index</feature> <symbol>&gt;</symbol> <number>0</number> <keyword>and then</keyword> <feature><location>../implementation_interface/ev_dynamic_list_i.xml#f_index</location>index</feature> <symbol>&lt;=</symbol> <feature><location>../implementation_interface/ev_dynamic_list_i.xml#f_count</location>count</feature>
		<keyword>do</keyword>
			<keyword>Result</keyword> <symbol>:=</symbol> <feature><location>../implementation_interface/ev_dynamic_list_i.xml#f_i_th</location>i_th</feature><symbol> </symbol><symbol>(</symbol><feature><location>../implementation_interface/ev_dynamic_list_i.xml#f_index</location>index</feature><symbol>)</symbol>
		<keyword>end</keyword>

	<anchor>f_item</anchor><feature><location>../implementation_interface/ev_dynamic_list_i.xml#f_item</location>item</feature><symbol>:</symbol> <generic>G</generic>
			<comment>--</comment><comment> Current item</comment>
		<keyword>require</keyword>
			<tag>readable</tag><symbol>:</symbol> <feature><location>../implementation_interface/ev_dynamic_list_i.xml#f_index</location>index</feature> <symbol>&gt;</symbol> <number>0</number> <keyword>and then</keyword> <feature><location>../implementation_interface/ev_dynamic_list_i.xml#f_index</location>index</feature> <symbol>&lt;=</symbol> <feature><location>../implementation_interface/ev_dynamic_list_i.xml#f_count</location>count</feature>
		<keyword>do</keyword>
			<keyword>Result</keyword> <symbol>:=</symbol> <feature><location>../implementation_interface/ev_dynamic_list_i.xml#f_i_th</location>i_th</feature><symbol> </symbol><symbol>(</symbol><feature><location>../implementation_interface/ev_dynamic_list_i.xml#f_index</location>index</feature><symbol>)</symbol>
		<keyword>ensure</keyword>
			<tag>not_void</tag><symbol>:</symbol> <keyword>Result</keyword> <symbol>/=</symbol> <keyword>Void</keyword>
		<keyword>end</keyword>

	<anchor>f_index</anchor><feature><location>../implementation_interface/ev_dynamic_list_i.xml#f_index</location>index</feature><symbol>:</symbol> <class><include>False</include>INTEGER_32</class>
			<comment>--</comment><comment> Index of current position</comment>

	<anchor>f_cursor</anchor><feature><location>../implementation_interface/ev_dynamic_list_i.xml#f_cursor</location>cursor</feature><symbol>:</symbol> <class><location>../interface/ev_dynamic_list_cursor.xml</location>EV_DYNAMIC_LIST_CURSOR</class> <symbol>[</symbol><generic>G</generic><symbol>]</symbol>
			<comment>--</comment><comment> Current cursor position.</comment>
		<keyword>local</keyword>
			<local>an_item</local><symbol>:</symbol> <keyword>detachable</keyword> <keyword>like</keyword> <feature><location>../implementation_interface/ev_dynamic_list_i.xml#f_item</location>item</feature>
			<local>l_index</local><symbol>:</symbol> <class><include>False</include>INTEGER_32</class>
		<keyword>do</keyword>
			<local>l_index</local> <symbol>:=</symbol> <feature><location>../implementation_interface/ev_dynamic_list_i.xml#f_index</location>index</feature>
			<keyword>if</keyword> <local>l_index</local> <symbol>&gt;</symbol> <number>0</number> <keyword>and then</keyword> <local>l_index</local> <symbol>&lt;=</symbol> <feature><location>../implementation_interface/ev_dynamic_list_i.xml#f_count</location>count</feature> <keyword>then</keyword>
				<local>an_item</local> <symbol>:=</symbol> <feature><location>../implementation_interface/ev_dynamic_list_i.xml#f_item</location>item</feature>
			<keyword>end</keyword>
			<keyword>create</keyword> <keyword>Result</keyword><dot>.</dot><feature><location>../interface/ev_dynamic_list_cursor.xml#f_make</location>make</feature><symbol> </symbol><symbol>(</symbol><local>an_item</local><symbol>,</symbol> <local>l_index</local> <symbol>&lt;=</symbol> <number>0</number><symbol>,</symbol> <local>l_index</local> <symbol>&gt;</symbol> <feature><location>../implementation_interface/ev_dynamic_list_i.xml#f_count</location>count</feature><symbol>)</symbol>
		<keyword>ensure</keyword>
			<tag>not_void</tag><symbol>:</symbol> <keyword>Result</keyword> <symbol>/=</symbol> <keyword>Void</keyword>
		<keyword>end</keyword>

	<anchor>f_interface_i_th</anchor><feature><location>../implementation_interface/ev_dynamic_list_i.xml#f_interface_i_th</location>interface_i_th</feature> <symbol>(</symbol><local>i</local><symbol>:</symbol> <class><include>False</include>INTEGER_32</class><symbol>)</symbol><symbol>:</symbol> <generic>G</generic>
		<keyword>obsolete</keyword> &quot;Use `i_th' instead. [2017-05-31]&quot;
			<comment>--</comment><comment> Current i_th item but guaranteed attached for calling from interface only</comment>
		<keyword>require</keyword>
			<tag>readable</tag><symbol>:</symbol> <local>i</local> <symbol>&gt;</symbol> <number>0</number> <keyword>and then</keyword> <local>i</local> <symbol>&lt;=</symbol> <feature><location>../implementation_interface/ev_dynamic_list_i.xml#f_count</location>count</feature>
		<keyword>do</keyword>
			<keyword>Result</keyword> <symbol>:=</symbol> <feature><location>../implementation_interface/ev_dynamic_list_i.xml#f_i_th</location>i_th</feature><symbol> </symbol><symbol>(</symbol><local>i</local><symbol>)</symbol>
		<keyword>end</keyword>

	<anchor>f_i_th</anchor><feature><location>../implementation_interface/ev_dynamic_list_i.xml#f_i_th</location>i_th</feature> <symbol>(</symbol><local>i</local><symbol>:</symbol> <class><include>False</include>INTEGER_32</class><symbol>)</symbol><symbol>:</symbol> <generic>G</generic>
			<comment>--</comment><comment> Item at </comment><quoted>i</quoted><comment>-th position.</comment>
		<keyword>require</keyword>
			<tag>i_within_bounds</tag><symbol>:</symbol> <local>i</local> <symbol>&gt;</symbol> <number>0</number> <keyword>and then</keyword> <local>i</local> <symbol>&lt;=</symbol> <feature><location>../implementation_interface/ev_dynamic_list_i.xml#f_count</location>count</feature>
		<keyword>deferred</keyword>
		<keyword>ensure</keyword>
			<tag>not_void</tag><symbol>:</symbol> <keyword>Result</keyword> <symbol>/=</symbol> <keyword>Void</keyword>
		<keyword>end</keyword>

	<anchor>f_off</anchor><feature><location>../implementation_interface/ev_dynamic_list_i.xml#f_off</location>off</feature><symbol>:</symbol> <class><include>False</include>BOOLEAN</class>
			<comment>--</comment><comment> Is there no current item?</comment>
		<keyword>do</keyword>
			<keyword>Result</keyword> <symbol>:=</symbol> <symbol>(</symbol><feature><location>../implementation_interface/ev_dynamic_list_i.xml#f_index</location>index</feature> <symbol>=</symbol> <number>0</number><symbol>)</symbol> <keyword>or</keyword> <symbol>(</symbol><feature><location>../implementation_interface/ev_dynamic_list_i.xml#f_index</location>index</feature> <symbol>=</symbol> <feature><location>../implementation_interface/ev_dynamic_list_i.xml#f_count</location>count</feature> <symbol>+</symbol> <number>1</number><symbol>)</symbol>
		<keyword>end</keyword>

	<anchor>f_index_of</anchor><feature><location>../implementation_interface/ev_dynamic_list_i.xml#f_index_of</location>index_of</feature> <symbol>(</symbol><local>v</local><symbol>:</symbol> <keyword>detachable</keyword> <keyword>like</keyword> <feature><location>../implementation_interface/ev_dynamic_list_i.xml#f_item</location>item</feature><symbol>;</symbol> <local>i</local><symbol>:</symbol> <class><include>False</include>INTEGER_32</class><symbol>)</symbol><symbol>:</symbol> <class><include>False</include>INTEGER_32</class>
			<comment>--</comment><comment> Index of i_th item </comment><quoted>v</quoted><comment>, if present.</comment>
			<comment>--</comment><comment> As dynamic list descendants are all sets,</comment>
			<comment>--</comment><comment> Result will be zero for all values of </comment><quoted>i</quoted>
			<comment>--</comment><comment> that are not equal to one</comment>
		<keyword>require</keyword>
			<tag>positive_occurrences</tag><symbol>:</symbol> <local>i</local> <symbol>&gt;</symbol> <number>0</number>
		<keyword>local</keyword>
			<local>an_index</local><symbol>:</symbol> <class><include>False</include>INTEGER_32</class>
		<keyword>do</keyword>
			<keyword>if</keyword> <local>i</local> <symbol>=</symbol> <number>1</number> <keyword>then</keyword>
				<keyword>from</keyword>
					<local>an_index</local> <symbol>:=</symbol> <number>1</number>
				<keyword>until</keyword>
					<keyword>Result</keyword> <symbol>&gt;</symbol> <number>0</number> <keyword>or else</keyword> <local>an_index</local> <symbol>&gt;</symbol> <feature><location>../implementation_interface/ev_dynamic_list_i.xml#f_count</location>count</feature>
				<keyword>loop</keyword>
					<keyword>if</keyword> <feature><location>../implementation_interface/ev_dynamic_list_i.xml#f_i_th</location>i_th</feature><symbol> </symbol><symbol>(</symbol><local>an_index</local><symbol>)</symbol> <symbol>=</symbol> <local>v</local> <keyword>then</keyword>
						<keyword>Result</keyword> <symbol>:=</symbol> <local>an_index</local>
					<keyword>end</keyword>
					<local>an_index</local> <symbol>:=</symbol> <local>an_index</local> <symbol>+</symbol> <number>1</number>
				<keyword>end</keyword>
			<keyword>end</keyword>
		<keyword>end</keyword>

	<anchor>f_retrieve_item_by_data</anchor><feature><location>../implementation_interface/ev_dynamic_list_i.xml#f_retrieve_item_by_data</location>retrieve_item_by_data</feature> <symbol>(</symbol><local>data</local><symbol>:</symbol> <keyword>detachable</keyword> <class><include>False</include>ANY</class><symbol>;</symbol> <local>should_compare_objects</local><symbol>:</symbol> <class><include>False</include>BOOLEAN</class><symbol>)</symbol><symbol>:</symbol> <keyword>detachable</keyword> <generic>G</generic>
			<comment>--</comment><comment> </comment><quoted>Result</quoted><comment> is first item in </comment><quoted>Current</quoted><comment> with data</comment>
			<comment>--</comment><comment> matching </comment><quoted>some_data</quoted><comment>. Compare objects if</comment>
			<comment>--</comment><comment> </comment><quoted>should_compare_objects</quoted><comment> otherwise compare references.</comment>
		<keyword>local</keyword>
			<local>l_item</local><symbol>:</symbol> <keyword>like</keyword> <feature><location>../implementation_interface/ev_dynamic_list_i.xml#f_item</location>item</feature>
			<local>l_count</local><symbol>:</symbol> <keyword>like</keyword> <feature><location>../implementation_interface/ev_dynamic_list_i.xml#f_count</location>count</feature>
			<local>l_index</local><symbol>:</symbol> <keyword>like</keyword> <feature><location>../implementation_interface/ev_dynamic_list_i.xml#f_index</location>index</feature>
		<keyword>do</keyword>
			<keyword>from</keyword>
				<local>l_index</local> <symbol>:=</symbol> <number>1</number>
				<local>l_count</local> <symbol>:=</symbol> <feature><location>../implementation_interface/ev_dynamic_list_i.xml#f_count</location>count</feature>
			<keyword>until</keyword>
				<local>l_index</local> <symbol>=</symbol> <local>l_count</local> <symbol>+</symbol> <number>1</number> <keyword>or</keyword> <keyword>Result</keyword> <symbol>/=</symbol> <keyword>Void</keyword>
			<keyword>loop</keyword>
				<local>l_item</local> <symbol>:=</symbol> <feature><location>../implementation_interface/ev_dynamic_list_i.xml#f_i_th</location>i_th</feature><symbol> </symbol><symbol>(</symbol><local>l_index</local><symbol>)</symbol>
				<keyword>if</keyword> <symbol>(</symbol><local>should_compare_objects</local> <keyword>and then</keyword> <local>data</local> <symbol>~</symbol> <local>l_item</local><dot>.</dot><feature><location>../interface/ev_any.xml#f_data</location>data</feature><symbol>)</symbol> <keyword>or</keyword> <symbol>(</symbol><keyword>not</keyword> <local>should_compare_objects</local> <keyword>and</keyword> <local>data</local> <symbol>=</symbol> <local>l_item</local><dot>.</dot><feature><location>../interface/ev_any.xml#f_data</location>data</feature><symbol>)</symbol> <keyword>then</keyword>
					<keyword>Result</keyword> <symbol>:=</symbol> <local>l_item</local>
				<keyword>end</keyword>
				<local>l_index</local> <symbol>:=</symbol> <local>l_index</local> <symbol>+</symbol> <number>1</number>
			<keyword>end</keyword>
		<keyword>end</keyword>

	<anchor>f_retrieve_items_by_data</anchor><feature><location>../implementation_interface/ev_dynamic_list_i.xml#f_retrieve_items_by_data</location>retrieve_items_by_data</feature> <symbol>(</symbol><local>data</local><symbol>:</symbol> <class><include>False</include>ANY</class><symbol>;</symbol> <local>should_compare_objects</local><symbol>:</symbol> <class><include>False</include>BOOLEAN</class><symbol>)</symbol><symbol>:</symbol> <class><include>False</include>ARRAYED_LIST</class> <symbol>[</symbol><generic>G</generic><symbol>]</symbol>
			<comment>--</comment><comment> </comment><quoted>Result</quoted><comment> is all items in </comment><quoted>Current</quoted><comment> with data</comment>
			<comment>--</comment><comment> matching </comment><quoted>some_data</quoted><comment>. Compare objects if</comment>
			<comment>--</comment><comment> </comment><quoted>should_compare_objects</quoted><comment> otherwise compare references.</comment>
		<keyword>local</keyword>
			<local>l_item</local><symbol>:</symbol> <keyword>like</keyword> <feature><location>../implementation_interface/ev_dynamic_list_i.xml#f_item</location>item</feature>
			<local>l_index</local><symbol>:</symbol> <keyword>like</keyword> <feature><location>../implementation_interface/ev_dynamic_list_i.xml#f_index</location>index</feature>
			<local>l_count</local><symbol>:</symbol> <keyword>like</keyword> <feature><location>../implementation_interface/ev_dynamic_list_i.xml#f_count</location>count</feature>
		<keyword>do</keyword>
			<keyword>create</keyword> <keyword>Result</keyword><dot>.</dot><feature><include>False</include>make</feature><symbol> </symbol><symbol>(</symbol><number>0</number><symbol>)</symbol>
			<keyword>from</keyword>
				<local>l_index</local> <symbol>:=</symbol> <number>1</number>
				<local>l_count</local> <symbol>:=</symbol> <feature><location>../implementation_interface/ev_dynamic_list_i.xml#f_count</location>count</feature>
			<keyword>until</keyword>
				<local>l_index</local> <symbol>=</symbol> <local>l_count</local> <symbol>+</symbol> <number>1</number>
			<keyword>loop</keyword>
				<local>l_item</local> <symbol>:=</symbol> <feature><location>../implementation_interface/ev_dynamic_list_i.xml#f_i_th</location>i_th</feature><symbol> </symbol><symbol>(</symbol><local>l_index</local><symbol>)</symbol>
				<keyword>check</keyword>
						<local>l_item</local> <symbol>/=</symbol> <keyword>Void</keyword>
				<keyword>end</keyword>
				<keyword>if</keyword> <symbol>(</symbol><local>should_compare_objects</local> <keyword>and then</keyword> <local>data</local> <symbol>~</symbol> <local>l_item</local><dot>.</dot><feature><location>../interface/ev_any.xml#f_data</location>data</feature><symbol>)</symbol> <keyword>or</keyword> <symbol>(</symbol><keyword>not</keyword> <local>should_compare_objects</local> <keyword>and</keyword> <local>data</local> <symbol>=</symbol> <local>l_item</local><dot>.</dot><feature><location>../interface/ev_any.xml#f_data</location>data</feature><symbol>)</symbol> <keyword>then</keyword>
					<keyword>Result</keyword><dot>.</dot><feature><include>False</include>extend</feature><symbol> </symbol><symbol>(</symbol><local>l_item</local><symbol>)</symbol>
				<keyword>end</keyword>
				<local>l_index</local> <symbol>:=</symbol> <local>l_index</local> <symbol>+</symbol> <number>1</number>
			<keyword>end</keyword>
		<keyword>end</keyword>
	
<keyword>feature</keyword> <comment>--</comment><comment> Measurement</comment>

	<anchor>f_count</anchor><feature><location>../implementation_interface/ev_dynamic_list_i.xml#f_count</location>count</feature><symbol>:</symbol> <class><include>False</include>INTEGER_32</class>
			<comment>--</comment><comment> Number of items.</comment>
		<keyword>deferred</keyword>
		<keyword>end</keyword>
	
<keyword>feature</keyword> <comment>--</comment><comment> Status report</comment>

	<anchor>f_valid_cursor</anchor><feature><location>../implementation_interface/ev_dynamic_list_i.xml#f_valid_cursor</location>valid_cursor</feature> <symbol>(</symbol><local>p</local><symbol>:</symbol> <class><include>False</include>CURSOR</class><symbol>)</symbol><symbol>:</symbol> <class><include>False</include>BOOLEAN</class>
			<comment>--</comment><comment> Can the cursor be moved to position </comment><quoted>p</quoted><comment>?</comment>
			<comment>--</comment><comment> This is True if </comment><quoted>p</quoted><comment> conforms to EV_DYNAMIC_LIST_CURSOR and</comment>
			<comment>--</comment><comment> if it points to an item, </comment><quoted>Current</quoted><comment> must have it.</comment>
		<keyword>do</keyword>
			<keyword>Result</keyword> <symbol>:=</symbol> <keyword>attached</keyword> <symbol>{</symbol><keyword>like</keyword> <feature><location>../implementation_interface/ev_dynamic_list_i.xml#f_cursor</location>cursor</feature><symbol>}</symbol> <local>p</local> <keyword>as</keyword> dlc <keyword>and then</keyword> <symbol>(</symbol><local>dlc</local><dot>.</dot><feature><location>../interface/ev_dynamic_list_cursor.xml#f_item</location>item</feature> <symbol>=</symbol> <keyword>Void</keyword> <keyword>or else</keyword> <symbol>(</symbol><keyword>attached</keyword> <local>dlc</local><dot>.</dot><feature><location>../interface/ev_dynamic_list_cursor.xml#f_item</location>item</feature> <keyword>as</keyword> l_dlc_item <keyword>and then</keyword> <feature><location>../implementation_interface/ev_dynamic_list_i.xml#f_has</location>has</feature><symbol> </symbol><symbol>(</symbol><local>l_dlc_item</local><symbol>)</symbol><symbol>)</symbol><symbol>)</symbol>
		<keyword>end</keyword>

	<anchor>f_has</anchor><feature><location>../implementation_interface/ev_dynamic_list_i.xml#f_has</location>has</feature> <symbol>(</symbol><local>v</local><symbol>:</symbol> <keyword>detachable</keyword> <keyword>like</keyword> <feature><location>../implementation_interface/ev_dynamic_list_i.xml#f_item</location>item</feature><symbol>)</symbol><symbol>:</symbol> <class><include>False</include>BOOLEAN</class>
			<comment>--</comment><comment> Does structure contain </comment><quoted>v</quoted><comment>?</comment>
		<keyword>local</keyword>
			<local>i</local><symbol>:</symbol> <class><include>False</include>INTEGER_32</class>
		<keyword>do</keyword>
			<keyword>from</keyword>
				<local>i</local> <symbol>:=</symbol> <number>1</number>
			<keyword>until</keyword>
				<keyword>Result</keyword> <keyword>or else</keyword> <local>i</local> <symbol>&gt;</symbol> <feature><location>../implementation_interface/ev_dynamic_list_i.xml#f_count</location>count</feature>
			<keyword>loop</keyword>
				<keyword>Result</keyword> <symbol>:=</symbol> <feature><location>../implementation_interface/ev_dynamic_list_i.xml#f_i_th</location>i_th</feature><symbol> </symbol><symbol>(</symbol><local>i</local><symbol>)</symbol> <symbol>=</symbol> <local>v</local>
				<local>i</local> <symbol>:=</symbol> <local>i</local> <symbol>+</symbol> <number>1</number>
			<keyword>end</keyword>
		<keyword>end</keyword>
	
<keyword>feature</keyword> <comment>--</comment><comment> Cursor movement</comment>

	<anchor>f_start</anchor><feature><location>../implementation_interface/ev_dynamic_list_i.xml#f_start</location>start</feature>
			<comment>--</comment><comment> Move cursor to first position.</comment>
		<keyword>do</keyword>
			<feature><location>../implementation_interface/ev_dynamic_list_i.xml#f_index</location>index</feature> <symbol>:=</symbol> <number>1</number>
		<keyword>ensure</keyword>
			<tag>index_on_first</tag><symbol>:</symbol> <feature><location>../implementation_interface/ev_dynamic_list_i.xml#f_index</location>index</feature> <symbol>=</symbol> <number>1</number>
		<keyword>end</keyword>

	<anchor>f_back</anchor><feature><location>../implementation_interface/ev_dynamic_list_i.xml#f_back</location>back</feature>
			<comment>--</comment><comment> Move to previous item.</comment>
		<keyword>require</keyword>
			<tag>not_before</tag><symbol>:</symbol> <feature><location>../implementation_interface/ev_dynamic_list_i.xml#f_index</location>index</feature> <symbol>&gt;</symbol> <number>0</number>
		<keyword>do</keyword>
			<feature><location>../implementation_interface/ev_dynamic_list_i.xml#f_index</location>index</feature> <symbol>:=</symbol> <feature><location>../implementation_interface/ev_dynamic_list_i.xml#f_index</location>index</feature> <symbol>-</symbol> <number>1</number>
		<keyword>end</keyword>

	<anchor>f_forth</anchor><feature><location>../implementation_interface/ev_dynamic_list_i.xml#f_forth</location>forth</feature>
			<comment>--</comment><comment> Move cursor to next position.</comment>
		<keyword>require</keyword>
			<tag>not_after</tag><symbol>:</symbol> <feature><location>../implementation_interface/ev_dynamic_list_i.xml#f_index</location>index</feature> <symbol>&lt;=</symbol> <feature><location>../implementation_interface/ev_dynamic_list_i.xml#f_count</location>count</feature>
		<keyword>do</keyword>
			<feature><location>../implementation_interface/ev_dynamic_list_i.xml#f_index</location>index</feature> <symbol>:=</symbol> <feature><location>../implementation_interface/ev_dynamic_list_i.xml#f_index</location>index</feature> <symbol>+</symbol> <number>1</number>
		<keyword>end</keyword>

	<anchor>f_go_i_th</anchor><feature><location>../implementation_interface/ev_dynamic_list_i.xml#f_go_i_th</location>go_i_th</feature> <symbol>(</symbol><local>i</local><symbol>:</symbol> <class><include>False</include>INTEGER_32</class><symbol>)</symbol>
			<comment>--</comment><comment> Move cursor to </comment><quoted>i</quoted><comment>-th position.</comment>
		<keyword>do</keyword>
			<feature><location>../implementation_interface/ev_dynamic_list_i.xml#f_index</location>index</feature> <symbol>:=</symbol> <local>i</local>
			<keyword>if</keyword> <feature><location>../implementation_interface/ev_dynamic_list_i.xml#f_index</location>index</feature> <symbol>&lt;</symbol> <number>0</number> <keyword>then</keyword>
				<feature><location>../implementation_interface/ev_dynamic_list_i.xml#f_index</location>index</feature> <symbol>:=</symbol> <number>0</number>
			<keyword>elseif</keyword> <feature><location>../implementation_interface/ev_dynamic_list_i.xml#f_index</location>index</feature> <symbol>&gt;</symbol> <feature><location>../implementation_interface/ev_dynamic_list_i.xml#f_count</location>count</feature> <symbol>+</symbol> <number>1</number> <keyword>then</keyword>
				<feature><location>../implementation_interface/ev_dynamic_list_i.xml#f_index</location>index</feature> <symbol>:=</symbol> <feature><location>../implementation_interface/ev_dynamic_list_i.xml#f_count</location>count</feature> <symbol>+</symbol> <number>1</number>
			<keyword>end</keyword>
		<keyword>end</keyword>

	<anchor>f_go_to</anchor><feature><location>../implementation_interface/ev_dynamic_list_i.xml#f_go_to</location>go_to</feature> <symbol>(</symbol><local>p</local><symbol>:</symbol> <class><include>False</include>CURSOR</class><symbol>)</symbol>
			<comment>--</comment><comment> Move cursor to position </comment><quoted>p</quoted><comment>.</comment>
		<keyword>local</keyword>
			<local>dlc</local><symbol>:</symbol> <keyword>detachable</keyword> <class><location>../interface/ev_dynamic_list_cursor.xml</location>EV_DYNAMIC_LIST_CURSOR</class> <symbol>[</symbol><generic>G</generic><symbol>]</symbol>
		<keyword>do</keyword>
			<local>dlc</local> <symbol>?=</symbol> <local>p</local>
			<keyword>check</keyword>
				<tag>dlc_not_void</tag><symbol>:</symbol> <local>dlc</local> <symbol>/=</symbol> <keyword>Void</keyword>
			<keyword>then</keyword>
			<keyword>end</keyword>
			<keyword>if</keyword> <local>dlc</local><dot>.</dot><feature><location>../interface/ev_dynamic_list_cursor.xml#f_after</location>after</feature> <keyword>then</keyword>
				<feature><location>../implementation_interface/ev_dynamic_list_i.xml#f_index</location>index</feature> <symbol>:=</symbol> <feature><location>../implementation_interface/ev_dynamic_list_i.xml#f_count</location>count</feature> <symbol>+</symbol> <number>1</number>
			<keyword>elseif</keyword> <local>dlc</local><dot>.</dot><feature><location>../interface/ev_dynamic_list_cursor.xml#f_before</location>before</feature> <keyword>then</keyword>
				<feature><location>../implementation_interface/ev_dynamic_list_i.xml#f_index</location>index</feature> <symbol>:=</symbol> <number>0</number>
			<keyword>elseif</keyword> <keyword>attached</keyword> <local>dlc</local><dot>.</dot><feature><location>../interface/ev_dynamic_list_cursor.xml#f_item</location>item</feature> <keyword>as</keyword> l_item <keyword>then</keyword>
				<feature><location>../implementation_interface/ev_dynamic_list_i.xml#f_index</location>index</feature> <symbol>:=</symbol> <feature><location>../implementation_interface/ev_dynamic_list_i.xml#f_index_of</location>index_of</feature><symbol> </symbol><symbol>(</symbol><local>l_item</local><symbol>,</symbol> <number>1</number><symbol>)</symbol>
			<keyword>else</keyword>
				<keyword>check</keyword>
						<keyword>False</keyword>
				<keyword>end</keyword>
			<keyword>end</keyword>
		<keyword>end</keyword>

	<anchor>f_move</anchor><feature><location>../implementation_interface/ev_dynamic_list_i.xml#f_move</location>move</feature> <symbol>(</symbol><local>i</local><symbol>:</symbol> <class><include>False</include>INTEGER_32</class><symbol>)</symbol>
			<comment>--</comment><comment> Move cursor </comment><quoted>i</quoted><comment> positions.</comment>
		<keyword>do</keyword>
			<feature><location>../implementation_interface/ev_dynamic_list_i.xml#f_index</location>index</feature> <symbol>:=</symbol> <feature><location>../implementation_interface/ev_dynamic_list_i.xml#f_index</location>index</feature> <symbol>+</symbol> <local>i</local>
			<keyword>if</keyword> <feature><location>../implementation_interface/ev_dynamic_list_i.xml#f_index</location>index</feature> <symbol>&lt;</symbol> <number>0</number> <keyword>then</keyword>
				<feature><location>../implementation_interface/ev_dynamic_list_i.xml#f_index</location>index</feature> <symbol>:=</symbol> <number>0</number>
			<keyword>elseif</keyword> <feature><location>../implementation_interface/ev_dynamic_list_i.xml#f_index</location>index</feature> <symbol>&gt;</symbol> <feature><location>../implementation_interface/ev_dynamic_list_i.xml#f_count</location>count</feature> <symbol>+</symbol> <number>1</number> <keyword>then</keyword>
				<feature><location>../implementation_interface/ev_dynamic_list_i.xml#f_index</location>index</feature> <symbol>:=</symbol> <feature><location>../implementation_interface/ev_dynamic_list_i.xml#f_count</location>count</feature> <symbol>+</symbol> <number>1</number>
			<keyword>end</keyword>
		<keyword>end</keyword>
	
<keyword>feature</keyword> <comment>--</comment><comment> Element change</comment>

	<anchor>f_append</anchor><feature><location>../implementation_interface/ev_dynamic_list_i.xml#f_append</location>append</feature> <symbol>(</symbol><local>s</local><symbol>:</symbol> <class><include>False</include>SEQUENCE</class> <symbol>[</symbol><generic>G</generic><symbol>]</symbol><symbol>)</symbol>
			<comment>--</comment><comment> Append a copy of </comment><quoted>s</quoted><comment>. Do not move cursor.</comment>
		<keyword>require</keyword>
			<tag>sequence_not_void</tag><symbol>:</symbol> <local>s</local> <symbol>/=</symbol> <keyword>Void</keyword>
		<keyword>do</keyword>
			<keyword>from</keyword>
				<local>s</local><dot>.</dot><feature><include>False</include>start</feature>
			<keyword>until</keyword>
				<local>s</local><dot>.</dot><feature><include>False</include>off</feature>
			<keyword>loop</keyword>
				<feature><location>../implementation_interface/ev_dynamic_list_i.xml#f_extend</location>extend</feature><symbol> </symbol><symbol>(</symbol><local>s</local><dot>.</dot><feature><include>False</include>item</feature><symbol>)</symbol>
				<local>s</local><dot>.</dot><feature><include>False</include>forth</feature>
			<keyword>end</keyword>
		<keyword>ensure</keyword>
			<tag>count_increased</tag><symbol>:</symbol> <keyword>old</keyword> <feature><location>../implementation_interface/ev_dynamic_list_i.xml#f_count</location>count</feature> <symbol>+</symbol> <local>s</local><dot>.</dot><feature><include>False</include>count</feature> <symbol>=</symbol> <feature><location>../implementation_interface/ev_dynamic_list_i.xml#f_count</location>count</feature>
		<keyword>end</keyword>

	<anchor>f_extend</anchor><feature><location>../implementation_interface/ev_dynamic_list_i.xml#f_extend</location>extend</feature> <symbol>(</symbol><local>v</local><symbol>:</symbol> <keyword>like</keyword> <feature><location>../implementation_interface/ev_dynamic_list_i.xml#f_item</location>item</feature><symbol>)</symbol>
			<comment>--</comment><comment> Add </comment><quoted>v</quoted><comment> to end. Do not move cursor.</comment>
		<keyword>require</keyword>
			<tag>v_not_void</tag><symbol>:</symbol> <local>v</local> <symbol>/=</symbol> <keyword>Void</keyword>
		<keyword>do</keyword>
			<feature><location>../implementation_interface/ev_dynamic_list_i.xml#f_insert_i_th</location>insert_i_th</feature><symbol> </symbol><symbol>(</symbol><local>v</local><symbol>,</symbol> <feature><location>../implementation_interface/ev_dynamic_list_i.xml#f_count</location>count</feature> <symbol>+</symbol> <number>1</number><symbol>)</symbol>
			<keyword>if</keyword> <feature><location>../implementation_interface/ev_dynamic_list_i.xml#f_index</location>index</feature> <symbol>=</symbol> <feature><location>../implementation_interface/ev_dynamic_list_i.xml#f_count</location>count</feature> <keyword>then</keyword>
				<feature><location>../implementation_interface/ev_dynamic_list_i.xml#f_index</location>index</feature> <symbol>:=</symbol> <feature><location>../implementation_interface/ev_dynamic_list_i.xml#f_index</location>index</feature> <symbol>+</symbol> <number>1</number>
			<keyword>end</keyword>
		<keyword>ensure</keyword>
			<tag>has_v</tag><symbol>:</symbol> <feature><location>../implementation_interface/ev_dynamic_list_i.xml#f_has</location>has</feature><symbol> </symbol><symbol>(</symbol><local>v</local><symbol>)</symbol>
		<keyword>end</keyword>

	<anchor>f_replace</anchor><feature><location>../implementation_interface/ev_dynamic_list_i.xml#f_replace</location>replace</feature> <symbol>(</symbol><local>v</local><symbol>:</symbol> <keyword>like</keyword> <feature><location>../implementation_interface/ev_dynamic_list_i.xml#f_item</location>item</feature><symbol>)</symbol>
			<comment>--</comment><comment> Replace current item by </comment><quoted>v</quoted><comment>.</comment>
		<keyword>require</keyword>
			<tag>writable</tag><symbol>:</symbol> <feature><location>../implementation_interface/ev_dynamic_list_i.xml#f_index</location>index</feature> <symbol>&gt;</symbol> <number>0</number> <keyword>and then</keyword> <feature><location>../implementation_interface/ev_dynamic_list_i.xml#f_index</location>index</feature> <symbol>&lt;=</symbol> <feature><location>../implementation_interface/ev_dynamic_list_i.xml#f_count</location>count</feature>
			<tag>v_not_void</tag><symbol>:</symbol> <local>v</local> <symbol>/=</symbol> <keyword>Void</keyword>
		<keyword>do</keyword>
			<feature><location>../implementation_interface/ev_dynamic_list_i.xml#f_remove_i_th</location>remove_i_th</feature><symbol> </symbol><symbol>(</symbol><feature><location>../implementation_interface/ev_dynamic_list_i.xml#f_index</location>index</feature><symbol>)</symbol>
			<feature><location>../implementation_interface/ev_dynamic_list_i.xml#f_insert_i_th</location>insert_i_th</feature><symbol> </symbol><symbol>(</symbol><local>v</local><symbol>,</symbol> <feature><location>../implementation_interface/ev_dynamic_list_i.xml#f_index</location>index</feature><symbol>)</symbol>
		<keyword>ensure</keyword>
			<tag>has_v</tag><symbol>:</symbol> <feature><location>../implementation_interface/ev_dynamic_list_i.xml#f_has</location>has</feature><symbol> </symbol><symbol>(</symbol><local>v</local><symbol>)</symbol>
		<keyword>end</keyword>

	<anchor>f_put_front</anchor><feature><location>../implementation_interface/ev_dynamic_list_i.xml#f_put_front</location>put_front</feature> <symbol>(</symbol><local>v</local><symbol>:</symbol> <keyword>like</keyword> <feature><location>../implementation_interface/ev_dynamic_list_i.xml#f_item</location>item</feature><symbol>)</symbol>
			<comment>--</comment><comment> Add </comment><quoted>v</quoted><comment> at beginning. Do not move cursor.</comment>
		<keyword>require</keyword>
			<tag>v_not_void</tag><symbol>:</symbol> <local>v</local> <symbol>/=</symbol> <keyword>Void</keyword>
		<keyword>do</keyword>
			<feature><location>../implementation_interface/ev_dynamic_list_i.xml#f_insert_i_th</location>insert_i_th</feature><symbol> </symbol><symbol>(</symbol><local>v</local><symbol>,</symbol> <number>1</number><symbol>)</symbol>
			<keyword>if</keyword> <feature><location>../implementation_interface/ev_dynamic_list_i.xml#f_index</location>index</feature> <symbol>&gt;</symbol> <number>0</number> <keyword>then</keyword>
				<feature><location>../implementation_interface/ev_dynamic_list_i.xml#f_index</location>index</feature> <symbol>:=</symbol> <feature><location>../implementation_interface/ev_dynamic_list_i.xml#f_index</location>index</feature> <symbol>+</symbol> <number>1</number>
			<keyword>end</keyword>
		<keyword>ensure</keyword>
			<tag>has_v</tag><symbol>:</symbol> <feature><location>../implementation_interface/ev_dynamic_list_i.xml#f_has</location>has</feature><symbol> </symbol><symbol>(</symbol><local>v</local><symbol>)</symbol>
		<keyword>end</keyword>

	<anchor>f_put_right</anchor><feature><location>../implementation_interface/ev_dynamic_list_i.xml#f_put_right</location>put_right</feature> <symbol>(</symbol><local>v</local><symbol>:</symbol> <keyword>like</keyword> <feature><location>../implementation_interface/ev_dynamic_list_i.xml#f_item</location>item</feature><symbol>)</symbol>
			<comment>--</comment><comment> Add </comment><quoted>v</quoted><comment> to the right of cursor position. Do not move cursor.</comment>
		<keyword>require</keyword>
			<tag>v_not_void</tag><symbol>:</symbol> <local>v</local> <symbol>/=</symbol> <keyword>Void</keyword>
		<keyword>do</keyword>
			<feature><location>../implementation_interface/ev_dynamic_list_i.xml#f_insert_i_th</location>insert_i_th</feature><symbol> </symbol><symbol>(</symbol><local>v</local><symbol>,</symbol> <feature><location>../implementation_interface/ev_dynamic_list_i.xml#f_index</location>index</feature> <symbol>+</symbol> <number>1</number><symbol>)</symbol>
		<keyword>ensure</keyword>
			<tag>has_v</tag><symbol>:</symbol> <feature><location>../implementation_interface/ev_dynamic_list_i.xml#f_has</location>has</feature><symbol> </symbol><symbol>(</symbol><local>v</local><symbol>)</symbol>
		<keyword>end</keyword>

	<anchor>f_put_left</anchor><feature><location>../implementation_interface/ev_dynamic_list_i.xml#f_put_left</location>put_left</feature> <symbol>(</symbol><local>v</local><symbol>:</symbol> <keyword>like</keyword> <feature><location>../implementation_interface/ev_dynamic_list_i.xml#f_item</location>item</feature><symbol>)</symbol>
			<comment>--</comment><comment> Add </comment><quoted>v</quoted><comment> to the left of cursor position. Do not move cursor.</comment>
		<keyword>require</keyword>
			<tag>v_not_void</tag><symbol>:</symbol> <local>v</local> <symbol>/=</symbol> <keyword>Void</keyword>
		<keyword>do</keyword>
			<feature><location>../implementation_interface/ev_dynamic_list_i.xml#f_insert_i_th</location>insert_i_th</feature><symbol> </symbol><symbol>(</symbol><local>v</local><symbol>,</symbol> <feature><location>../implementation_interface/ev_dynamic_list_i.xml#f_index</location>index</feature><symbol>)</symbol>
			<feature><location>../implementation_interface/ev_dynamic_list_i.xml#f_index</location>index</feature> <symbol>:=</symbol> <feature><location>../implementation_interface/ev_dynamic_list_i.xml#f_index</location>index</feature> <symbol>+</symbol> <number>1</number>
		<keyword>ensure</keyword>
			<tag>has_v</tag><symbol>:</symbol> <feature><location>../implementation_interface/ev_dynamic_list_i.xml#f_has</location>has</feature><symbol> </symbol><symbol>(</symbol><local>v</local><symbol>)</symbol>
		<keyword>end</keyword>

	<anchor>f_put_i_th</anchor><feature><location>../implementation_interface/ev_dynamic_list_i.xml#f_put_i_th</location>put_i_th</feature> <symbol>(</symbol><local>v</local><symbol>:</symbol> <keyword>like</keyword> <feature><location>../implementation_interface/ev_dynamic_list_i.xml#f_item</location>item</feature><symbol>;</symbol> <local>i</local><symbol>:</symbol> <class><include>False</include>INTEGER_32</class><symbol>)</symbol>
			<comment>--</comment><comment> Replace item at </comment><quoted>i</quoted><comment>-th position by </comment><quoted>v</quoted><comment>.</comment>
		<keyword>require</keyword>
			<tag>valid_index</tag><symbol>:</symbol> <local>i</local> <symbol>&gt;</symbol> <number>0</number> <keyword>and</keyword> <local>i</local> <symbol>&lt;=</symbol> <feature><location>../implementation_interface/ev_dynamic_list_i.xml#f_count</location>count</feature>
			<tag>v_not_void</tag><symbol>:</symbol> <local>v</local> <symbol>/=</symbol> <keyword>Void</keyword>
		<keyword>do</keyword>
			<feature><location>../implementation_interface/ev_dynamic_list_i.xml#f_insert_i_th</location>insert_i_th</feature><symbol> </symbol><symbol>(</symbol><local>v</local><symbol>,</symbol> <local>i</local><symbol>)</symbol>
			<feature><location>../implementation_interface/ev_dynamic_list_i.xml#f_remove_i_th</location>remove_i_th</feature><symbol> </symbol><symbol>(</symbol><local>i</local> <symbol>+</symbol> <number>1</number><symbol>)</symbol>
		<keyword>ensure</keyword>
			<tag>has_v</tag><symbol>:</symbol> <feature><location>../implementation_interface/ev_dynamic_list_i.xml#f_has</location>has</feature><symbol> </symbol><symbol>(</symbol><local>v</local><symbol>)</symbol>
		<keyword>end</keyword>

	<anchor>f_merge_left</anchor><feature><location>../implementation_interface/ev_dynamic_list_i.xml#f_merge_left</location>merge_left</feature> <symbol>(</symbol><local>other</local><symbol>:</symbol> <keyword>like</keyword> <feature><location>../implementation_interface/ev_any_i.xml#f_attached_interface</location>attached_interface</feature><symbol>)</symbol>
			<comment>--</comment><comment> Merge </comment><quoted>other</quoted><comment> into current structure before cursor</comment>
			<comment>--</comment><comment> position. Do not move cursor. Empty </comment><quoted>other</quoted><comment>.</comment>
		<keyword>local</keyword>
			<local>v</local><symbol>:</symbol> <keyword>like</keyword> <feature><location>../implementation_interface/ev_dynamic_list_i.xml#f_item</location>item</feature>
		<keyword>do</keyword>
			<keyword>from</keyword>
				<local>other</local><dot>.</dot><feature><location>../interface/ev_dynamic_list.xml#f_start</location>start</feature>
			<keyword>until</keyword>
				<local>other</local><dot>.</dot><feature><include>False</include>is_empty</feature>
			<keyword>loop</keyword>
				<local>v</local> <symbol>:=</symbol> <local>other</local><dot>.</dot><feature><location>../interface/ev_dynamic_list.xml#f_item</location>item</feature>
				<keyword>check</keyword>
						<local>v</local> <symbol>/=</symbol> <keyword>Void</keyword>
				<keyword>end</keyword>
				<local>other</local><dot>.</dot><feature><location>../interface/ev_dynamic_list.xml#f_remove</location>remove</feature>
				<feature><location>../implementation_interface/ev_dynamic_list_i.xml#f_insert_i_th</location>insert_i_th</feature><symbol> </symbol><symbol>(</symbol><local>v</local><symbol>,</symbol> <feature><location>../implementation_interface/ev_dynamic_list_i.xml#f_index</location>index</feature><symbol>)</symbol>
				<feature><location>../implementation_interface/ev_dynamic_list_i.xml#f_index</location>index</feature> <symbol>:=</symbol> <feature><location>../implementation_interface/ev_dynamic_list_i.xml#f_index</location>index</feature> <symbol>+</symbol> <number>1</number>
			<keyword>end</keyword>
		<keyword>end</keyword>

	<anchor>f_merge_right</anchor><feature><location>../implementation_interface/ev_dynamic_list_i.xml#f_merge_right</location>merge_right</feature> <symbol>(</symbol><local>other</local><symbol>:</symbol> <keyword>like</keyword> <feature><location>../implementation_interface/ev_any_i.xml#f_attached_interface</location>attached_interface</feature><symbol>)</symbol>
			<comment>--</comment><comment> Merge </comment><quoted>other</quoted><comment> into current structure after cursor</comment>
			<comment>--</comment><comment> position. Do not move cursor. Empty </comment><quoted>other</quoted><comment>.</comment>
		<keyword>local</keyword>
			<local>v</local><symbol>:</symbol> <keyword>like</keyword> <feature><location>../implementation_interface/ev_dynamic_list_i.xml#f_item</location>item</feature>
		<keyword>do</keyword>
			<keyword>from</keyword>
			<keyword>until</keyword>
				<local>other</local><dot>.</dot><feature><include>False</include>is_empty</feature>
			<keyword>loop</keyword>
				<local>other</local><dot>.</dot><feature><include>False</include>finish</feature>
				<local>v</local> <symbol>:=</symbol> <local>other</local><dot>.</dot><feature><location>../interface/ev_dynamic_list.xml#f_item</location>item</feature>
				<keyword>check</keyword>
						<local>v</local> <symbol>/=</symbol> <keyword>Void</keyword>
				<keyword>end</keyword>
				<local>other</local><dot>.</dot><feature><location>../interface/ev_dynamic_list.xml#f_remove</location>remove</feature>
				<feature><location>../implementation_interface/ev_dynamic_list_i.xml#f_insert_i_th</location>insert_i_th</feature><symbol> </symbol><symbol>(</symbol><local>v</local><symbol>,</symbol> <feature><location>../implementation_interface/ev_dynamic_list_i.xml#f_index</location>index</feature> <symbol>+</symbol> <number>1</number><symbol>)</symbol>
			<keyword>end</keyword>
		<keyword>end</keyword>
	
<keyword>feature</keyword> <comment>--</comment><comment> Removal</comment>

	<anchor>f_prune</anchor><feature><location>../implementation_interface/ev_dynamic_list_i.xml#f_prune</location>prune</feature> <symbol>(</symbol><local>v</local><symbol>:</symbol> <keyword>like</keyword> <feature><location>../implementation_interface/ev_dynamic_list_i.xml#f_item</location>item</feature><symbol>)</symbol>
			<comment>--</comment><comment> Remove </comment><quoted>v</quoted><comment> if present. Do not move cursor, except if</comment>
			<comment>--</comment><comment> cursor was on </comment><quoted>v</quoted><comment>, move to right neighbor.</comment>
		<keyword>local</keyword>
			<local>item_index</local><symbol>:</symbol> <class><include>False</include>INTEGER_32</class>
		<keyword>do</keyword>
			<local>item_index</local> <symbol>:=</symbol> <feature><location>../implementation_interface/ev_dynamic_list_i.xml#f_index_of</location>index_of</feature><symbol> </symbol><symbol>(</symbol><local>v</local><symbol>,</symbol> <number>1</number><symbol>)</symbol>
			<keyword>if</keyword> <local>item_index</local> <symbol>&gt;</symbol> <number>0</number> <keyword>then</keyword>
				<keyword>if</keyword> <local>item_index</local> <symbol>&lt;=</symbol> <feature><location>../implementation_interface/ev_dynamic_list_i.xml#f_index</location>index</feature> <keyword>then</keyword>
					<feature><location>../implementation_interface/ev_dynamic_list_i.xml#f_index</location>index</feature> <symbol>:=</symbol> <feature><location>../implementation_interface/ev_dynamic_list_i.xml#f_index</location>index</feature> <symbol>-</symbol> <number>1</number>
				<keyword>end</keyword>
				<feature><location>../implementation_interface/ev_dynamic_list_i.xml#f_remove_i_th</location>remove_i_th</feature><symbol> </symbol><symbol>(</symbol><local>item_index</local><symbol>)</symbol>
			<keyword>end</keyword>
		<keyword>ensure</keyword>
			<tag>cursor_not_moved</tag><symbol>:</symbol> <keyword>not</keyword> <keyword>old</keyword> <feature><location>../implementation_interface/ev_dynamic_list_i.xml#f_has</location>has</feature><symbol> </symbol><symbol>(</symbol><local>v</local><symbol>)</symbol> <keyword>implies</keyword> <keyword>old</keyword> <feature><location>../implementation_interface/ev_any_i.xml#f_attached_interface</location>attached_interface</feature><dot>.</dot><feature><location>../interface/ev_dynamic_list.xml#f_index</location>index</feature> <symbol>=</symbol> <feature><location>../implementation_interface/ev_any_i.xml#f_attached_interface</location>attached_interface</feature><dot>.</dot><feature><location>../interface/ev_dynamic_list.xml#f_index</location>index</feature>
			<tag>cursor_not_moved</tag><symbol>:</symbol> <keyword>old</keyword> <feature><location>../implementation_interface/ev_dynamic_list_i.xml#f_has</location>has</feature><symbol> </symbol><symbol>(</symbol><local>v</local><symbol>)</symbol> <keyword>and then</keyword> <keyword>old</keyword> <feature><location>../implementation_interface/ev_any_i.xml#f_attached_interface</location>attached_interface</feature><dot>.</dot><feature><location>../interface/ev_dynamic_list.xml#f_index</location>index</feature> <symbol>&lt;</symbol> <keyword>old</keyword> <feature><location>../implementation_interface/ev_dynamic_list_i.xml#f_index_of</location>index_of</feature><symbol> </symbol><symbol>(</symbol><local>v</local><symbol>,</symbol> <number>1</number><symbol>)</symbol> <keyword>implies</keyword> <feature><location>../implementation_interface/ev_dynamic_list_i.xml#f_index</location>index</feature> <symbol>=</symbol> <keyword>old</keyword> <feature><location>../implementation_interface/ev_dynamic_list_i.xml#f_index</location>index</feature>
			<tag>cursor_not_moved</tag><symbol>:</symbol> <keyword>old</keyword> <feature><location>../implementation_interface/ev_dynamic_list_i.xml#f_has</location>has</feature><symbol> </symbol><symbol>(</symbol><local>v</local><symbol>)</symbol> <keyword>and then</keyword> <keyword>old</keyword> <feature><location>../implementation_interface/ev_any_i.xml#f_attached_interface</location>attached_interface</feature><dot>.</dot><feature><location>../interface/ev_dynamic_list.xml#f_index</location>index</feature> <symbol>&gt;=</symbol> <keyword>old</keyword> <feature><location>../implementation_interface/ev_dynamic_list_i.xml#f_index_of</location>index_of</feature><symbol> </symbol><symbol>(</symbol><local>v</local><symbol>,</symbol> <number>1</number><symbol>)</symbol> <keyword>implies</keyword> <feature><location>../implementation_interface/ev_dynamic_list_i.xml#f_index</location>index</feature> <symbol>=</symbol> <keyword>old</keyword> <feature><location>../implementation_interface/ev_dynamic_list_i.xml#f_index</location>index</feature> <symbol>-</symbol> <number>1</number>
			<tag>not_has_v</tag><symbol>:</symbol> <keyword>not</keyword> <feature><location>../implementation_interface/ev_dynamic_list_i.xml#f_has</location>has</feature><symbol> </symbol><symbol>(</symbol><local>v</local><symbol>)</symbol>
		<keyword>end</keyword>

	<anchor>f_remove</anchor><feature><location>../implementation_interface/ev_dynamic_list_i.xml#f_remove</location>remove</feature>
			<comment>--</comment><comment> Remove current item. Move cursor to right neighbor</comment>
			<comment>--</comment><comment> (or </comment><quoted>after</quoted><comment> if no right neighbor).</comment>
		<keyword>require</keyword>
			<tag>writable</tag><symbol>:</symbol> <keyword>not</keyword> <feature><location>../implementation_interface/ev_dynamic_list_i.xml#f_off</location>off</feature>
		<keyword>do</keyword>
			<feature><location>../implementation_interface/ev_dynamic_list_i.xml#f_remove_i_th</location>remove_i_th</feature><symbol> </symbol><symbol>(</symbol><feature><location>../implementation_interface/ev_dynamic_list_i.xml#f_index</location>index</feature><symbol>)</symbol>
			<keyword>if</keyword> <feature><location>../implementation_interface/ev_dynamic_list_i.xml#f_index</location>index</feature> <symbol>&gt;</symbol> <feature><location>../implementation_interface/ev_dynamic_list_i.xml#f_count</location>count</feature> <symbol>+</symbol> <number>1</number> <keyword>then</keyword>
				<feature><location>../implementation_interface/ev_dynamic_list_i.xml#f_index</location>index</feature> <symbol>:=</symbol> <feature><location>../implementation_interface/ev_dynamic_list_i.xml#f_count</location>count</feature> <symbol>+</symbol> <number>1</number>
			<keyword>end</keyword>
		<keyword>ensure</keyword>
			<tag>not_has_v</tag><symbol>:</symbol> <keyword>not</keyword> <feature><location>../implementation_interface/ev_dynamic_list_i.xml#f_has</location>has</feature><symbol> </symbol><symbol>(</symbol><keyword>old</keyword> <feature><location>../implementation_interface/ev_dynamic_list_i.xml#f_item</location>item</feature><symbol>)</symbol>
		<keyword>end</keyword>

	<anchor>f_remove_left</anchor><feature><location>../implementation_interface/ev_dynamic_list_i.xml#f_remove_left</location>remove_left</feature>
			<comment>--</comment><comment> Remove item to the left of cursor position.</comment>
			<comment>--</comment><comment> Do not move cursor.</comment>
		<keyword>require</keyword>
			<tag>left_exists</tag><symbol>:</symbol> <feature><location>../implementation_interface/ev_dynamic_list_i.xml#f_index</location>index</feature> <symbol>&gt;</symbol> <number>1</number>
			<tag>not_before</tag><symbol>:</symbol> <keyword>not</keyword> <symbol>(</symbol><feature><location>../implementation_interface/ev_dynamic_list_i.xml#f_index</location>index</feature> <symbol>=</symbol> <number>0</number><symbol>)</symbol>
		<keyword>do</keyword>
			<feature><location>../implementation_interface/ev_dynamic_list_i.xml#f_index</location>index</feature> <symbol>:=</symbol> <feature><location>../implementation_interface/ev_dynamic_list_i.xml#f_index</location>index</feature> <symbol>-</symbol> <number>1</number>
			<feature><location>../implementation_interface/ev_dynamic_list_i.xml#f_remove_i_th</location>remove_i_th</feature><symbol> </symbol><symbol>(</symbol><feature><location>../implementation_interface/ev_dynamic_list_i.xml#f_index</location>index</feature><symbol>)</symbol>
		<keyword>ensure then</keyword>
			<tag>left_neighbor_removed</tag><symbol>:</symbol> <keyword>not</keyword> <feature><location>../implementation_interface/ev_dynamic_list_i.xml#f_has</location>has</feature><symbol> </symbol><symbol>(</symbol><keyword>old</keyword> <feature><location>../implementation_interface/ev_dynamic_list_i.xml#f_i_th</location>i_th</feature><symbol> </symbol><symbol>(</symbol><feature><location>../implementation_interface/ev_dynamic_list_i.xml#f_index</location>index</feature> <symbol>-</symbol> <number>1</number><symbol>)</symbol><symbol>)</symbol>
		<keyword>end</keyword>

	<anchor>f_remove_right</anchor><feature><location>../implementation_interface/ev_dynamic_list_i.xml#f_remove_right</location>remove_right</feature>
			<comment>--</comment><comment> Remove item to the right of cursor position.</comment>
			<comment>--</comment><comment> Do not move cursor.</comment>
		<keyword>require</keyword>
			<tag>right_exists</tag><symbol>:</symbol> <feature><location>../implementation_interface/ev_dynamic_list_i.xml#f_index</location>index</feature> <symbol>&lt;</symbol> <feature><location>../implementation_interface/ev_dynamic_list_i.xml#f_count</location>count</feature>
		<keyword>do</keyword>
			<feature><location>../implementation_interface/ev_dynamic_list_i.xml#f_remove_i_th</location>remove_i_th</feature><symbol> </symbol><symbol>(</symbol><feature><location>../implementation_interface/ev_dynamic_list_i.xml#f_index</location>index</feature> <symbol>+</symbol> <number>1</number><symbol>)</symbol>
		<keyword>ensure then</keyword>
			<tag>right_neighbor_removed</tag><symbol>:</symbol> <keyword>not</keyword> <feature><location>../implementation_interface/ev_dynamic_list_i.xml#f_has</location>has</feature><symbol> </symbol><symbol>(</symbol><keyword>old</keyword> <feature><location>../implementation_interface/ev_dynamic_list_i.xml#f_i_th</location>i_th</feature><symbol> </symbol><symbol>(</symbol><feature><location>../implementation_interface/ev_dynamic_list_i.xml#f_index</location>index</feature> <symbol>+</symbol> <number>1</number><symbol>)</symbol><symbol>)</symbol>
		<keyword>end</keyword>

	<anchor>f_wipe_out</anchor><feature><location>../implementation_interface/ev_dynamic_list_i.xml#f_wipe_out</location>wipe_out</feature>
			<comment>--</comment><comment> Remove all items.</comment>
		<keyword>local</keyword>
			<local>l_index</local><symbol>:</symbol> <class><include>False</include>INTEGER_32</class>
		<keyword>do</keyword>
			<keyword>from</keyword>
				<local>l_index</local> <symbol>:=</symbol> <feature><location>../implementation_interface/ev_dynamic_list_i.xml#f_count</location>count</feature>
			<keyword>until</keyword>
				<local>l_index</local> <symbol>=</symbol> <number>0</number>
			<keyword>loop</keyword>
				<feature><location>../implementation_interface/ev_dynamic_list_i.xml#f_go_i_th</location>go_i_th</feature><symbol> </symbol><symbol>(</symbol><local>l_index</local><symbol>)</symbol>
				<feature><location>../implementation_interface/ev_dynamic_list_i.xml#f_remove</location>remove</feature>
				<local>l_index</local> <symbol>:=</symbol> <local>l_index</local> <symbol>-</symbol> <number>1</number>
			<keyword>end</keyword>
			<feature><location>../implementation_interface/ev_dynamic_list_i.xml#f_go_i_th</location>go_i_th</feature><symbol> </symbol><symbol>(</symbol><local>l_index</local><symbol>)</symbol>
		<keyword>end</keyword>
	
<keyword>feature</keyword> <symbol>{</symbol>NONE<symbol>}</symbol> <comment>--</comment><comment> Implementation</comment>

	<anchor>f_insert_i_th</anchor><feature><location>../implementation_interface/ev_dynamic_list_i.xml#f_insert_i_th</location>insert_i_th</feature> <symbol>(</symbol><local>v</local><symbol>:</symbol> <keyword>like</keyword> <feature><location>../implementation_interface/ev_dynamic_list_i.xml#f_item</location>item</feature><symbol>;</symbol> <local>i</local><symbol>:</symbol> <class><include>False</include>INTEGER_32</class><symbol>)</symbol>
			<comment>--</comment><comment> Insert </comment><quoted>v</quoted><comment> at position </comment><quoted>i</quoted><comment>.</comment>
		<keyword>require</keyword>
			<tag>i_within_bounds</tag><symbol>:</symbol> <local>i</local> <symbol>&gt;</symbol> <number>0</number> <keyword>and</keyword> <local>i</local> <symbol>&lt;=</symbol> <feature><location>../implementation_interface/ev_dynamic_list_i.xml#f_count</location>count</feature> <symbol>+</symbol> <number>1</number>
		<keyword>deferred</keyword>
		<keyword>ensure</keyword>
			<tag>count_increased</tag><symbol>:</symbol> <feature><location>../implementation_interface/ev_dynamic_list_i.xml#f_count</location>count</feature> <symbol>=</symbol> <keyword>old</keyword> <feature><location>../implementation_interface/ev_dynamic_list_i.xml#f_count</location>count</feature> <symbol>+</symbol> <number>1</number>
		<keyword>end</keyword>

	<anchor>f_remove_i_th</anchor><feature><location>../implementation_interface/ev_dynamic_list_i.xml#f_remove_i_th</location>remove_i_th</feature> <symbol>(</symbol><local>i</local><symbol>:</symbol> <class><include>False</include>INTEGER_32</class><symbol>)</symbol>
			<comment>--</comment><comment> Remove item at </comment><quoted>i</quoted><comment>-th position.</comment>
		<keyword>require</keyword>
			<tag>i_within_bounds</tag><symbol>:</symbol> <local>i</local> <symbol>&gt;</symbol> <number>0</number> <keyword>and</keyword> <local>i</local> <symbol>&lt;=</symbol> <feature><location>../implementation_interface/ev_dynamic_list_i.xml#f_count</location>count</feature>
		<keyword>deferred</keyword>
		<keyword>ensure</keyword>
			<tag>count_decreased</tag><symbol>:</symbol> <feature><location>../implementation_interface/ev_dynamic_list_i.xml#f_count</location>count</feature> <symbol>=</symbol> <keyword>old</keyword> <feature><location>../implementation_interface/ev_dynamic_list_i.xml#f_count</location>count</feature> <symbol>-</symbol> <number>1</number>
		<keyword>end</keyword>
	
<keyword>feature</keyword> <symbol>{</symbol><class><location>../interface/ev_any.xml</location>EV_ANY</class><symbol>,</symbol> <class><location>../implementation_interface/ev_any_i.xml</location>EV_ANY_I</class><symbol>}</symbol> <comment>--</comment><comment> Implementation</comment>

	<anchor>f_interface</anchor><feature><location>../implementation_interface/ev_dynamic_list_i.xml#f_interface</location>interface</feature><symbol>:</symbol> <keyword>detachable</keyword> <class><location>../interface/ev_dynamic_list.xml</location>EV_DYNAMIC_LIST</class> <symbol>[</symbol><generic>G</generic><symbol>]</symbol>
		<keyword>note</keyword>
			option: stable
		<keyword>attribute</keyword>
		<keyword>end</keyword>
	
<keyword>invariant</keyword>
	<tag>index_within_bounds</tag><symbol>:</symbol> <feature><location>../implementation_interface/ev_any_i.xml#f_is_usable</location>is_usable</feature> <keyword>implies</keyword> <symbol>(</symbol><feature><location>../implementation_interface/ev_dynamic_list_i.xml#f_index</location>index</feature> <symbol>&gt;=</symbol> <number>0</number> <keyword>and then</keyword> <feature><location>../implementation_interface/ev_dynamic_list_i.xml#f_index</location>index</feature> <symbol>&lt;=</symbol> <feature><location>../implementation_interface/ev_dynamic_list_i.xml#f_count</location>count</feature> <symbol>+</symbol> <number>1</number><symbol>)</symbol>

<keyword>note</keyword>
	<indexing_tag>copyright</indexing_tag><symbol>:</symbol> <string>&quot;Copyright (c) 1984-2013, Eiffel Software and others&quot;</string>
	<indexing_tag>license</indexing_tag><symbol>:</symbol> <string>&quot;Eiffel Forum License v2 (see </string><string><location>http://www.eiffel.com/licensing/forum.txt</location>http://www.eiffel.com/licensing/forum.txt</string><string>)&quot;</string>
	<indexing_tag>source</indexing_tag><symbol>:</symbol> <string>&quot;</string><string>[</string>
		<string>Eiffel Software</string>
		<string>5949 Hollister Ave., Goleta, CA 93117 USA</string>
		<string>Telephone 805-685-1006, Fax 805-685-6869</string>
		<string>Website </string><string><location>http://www.eiffel.com</location>http://www.eiffel.com</string>
		<string>Customer support </string><string><location>http://support.eiffel.com</location>http://support.eiffel.com</string>
	<string>]</string><string>&quot;</string>

<keyword>end</keyword> <comment>--</comment> <comment>class </comment><class><location>../implementation_interface/ev_dynamic_list_i.xml</location>EV_DYNAMIC_LIST_I</class></system>

