<system>
<keyword>note</keyword>
	<indexing_tag>description</indexing_tag><symbol>:</symbol> <string>&quot;Objects that hold the current formatting applied while loading a RTF file.&quot;</string>
	<indexing_tag>legal</indexing_tag><symbol>:</symbol> <string>&quot;See notice at end of class.&quot;</string>
	<indexing_tag>status</indexing_tag><symbol>:</symbol> <string>&quot;See notice at end of class.&quot;</string>
	<indexing_tag>author</indexing_tag><symbol>:</symbol> <string>&quot;&quot;</string>
	<indexing_tag>date</indexing_tag><symbol>:</symbol> <string>&quot;$Date: 2013-01-28 17:14:10 -0800 (Mon, 28 Jan 2013) $&quot;</string>
	<indexing_tag>revision</indexing_tag><symbol>:</symbol> <string>&quot;$Revision: 91071 $&quot;</string>

<keyword>class</keyword> 
	<class><location>../implementation_interface/rtf_format_i.xml</location>RTF_FORMAT_I</class>

<keyword>inherit</keyword>
	<class><location>../interface/ev_paragraph_constants.xml</location>EV_PARAGRAPH_CONSTANTS</class>
		<keyword>rename</keyword>
			<feature><location>../interface/ev_paragraph_constants.xml#f_alignment</location>Alignment</feature> <keyword>as</keyword> <feature><location>../interface/ev_paragraph_constants.xml#f_alignment</location>Alignment_constant</feature><symbol>,</symbol>
			<feature><location>../interface/ev_paragraph_constants.xml#f_left_margin</location>Left_margin</feature> <keyword>as</keyword> <feature><location>../interface/ev_paragraph_constants.xml#f_left_margin</location>Left_margin_constant</feature><symbol>,</symbol>
			<feature><location>../interface/ev_paragraph_constants.xml#f_right_margin</location>Right_margin</feature> <keyword>as</keyword> <feature><location>../interface/ev_paragraph_constants.xml#f_right_margin</location>Right_margin_constant</feature><symbol>,</symbol>
			<feature><location>../interface/ev_paragraph_constants.xml#f_top_spacing</location>Top_spacing</feature> <keyword>as</keyword> <feature><location>../interface/ev_paragraph_constants.xml#f_top_spacing</location>Top_spacing_constant</feature><symbol>,</symbol>
			<feature><location>../interface/ev_paragraph_constants.xml#f_bottom_spacing</location>Bottom_spacing</feature> <keyword>as</keyword> <feature><location>../interface/ev_paragraph_constants.xml#f_bottom_spacing</location>Bottom_spacing_constant</feature>
		<keyword>redefine</keyword>
			<feature><location>../implementation_interface/rtf_format_i.xml#f_default_create</location>default_create</feature>
		<keyword>end</keyword>

<keyword>create</keyword> 
	<feature><location>../implementation_interface/rtf_format_i.xml#f_default_create</location>default_create</feature>

<keyword>feature</keyword> <symbol>{</symbol>NONE<symbol>}</symbol> <comment>--</comment><comment> Initialization</comment>

	<anchor>f_default_create</anchor><feature><location>../implementation_interface/rtf_format_i.xml#f_default_create</location>default_create</feature>
			<comment>--</comment><comment> Create </comment><quoted>Current</quoted>
		<keyword>do</keyword>
			<feature><location>../implementation_interface/rtf_format_i.xml#f_alignment</location>alignment</feature> <symbol>:=</symbol> <feature><location>../interface/ev_paragraph_constants.xml#f_alignment_left</location>Alignment_left</feature>
			<feature><location>../implementation_interface/rtf_format_i.xml#f_reset_internals</location>reset_internals</feature>
		<keyword>end</keyword>
	
<keyword>feature</keyword> <comment>--</comment><comment> Access</comment>

	<anchor>f_highlight_color</anchor><feature><location>../implementation_interface/rtf_format_i.xml#f_highlight_color</location>highlight_color</feature><symbol>:</symbol> <class><include>False</include>INTEGER_32</class>
			<comment>--</comment><comment> Highlighting applied to text.</comment>

	<anchor>f_highlight_set</anchor><feature><location>../implementation_interface/rtf_format_i.xml#f_highlight_set</location>highlight_set</feature><symbol>:</symbol> <class><include>False</include>BOOLEAN</class>
			<comment>--</comment><comment> Has </comment><feature><location>../implementation_interface/rtf_format_i.xml#f_highlight_color</location>highlight_color</feature><comment> been explicitly set and does not correspond to auto?</comment>

	<anchor>f_text_color</anchor><feature><location>../implementation_interface/rtf_format_i.xml#f_text_color</location>text_color</feature><symbol>:</symbol> <class><include>False</include>INTEGER_32</class>
			<comment>--</comment><comment> Text color of format</comment>

	<anchor>f_color_set</anchor><feature><location>../implementation_interface/rtf_format_i.xml#f_color_set</location>color_set</feature><symbol>:</symbol> <class><include>False</include>BOOLEAN</class>
			<comment>--</comment><comment> Has </comment><feature><location>../implementation_interface/rtf_format_i.xml#f_text_color</location>text_color</feature><comment> been explicitly set and does not correspond to auto?</comment>

	<anchor>f_is_bold</anchor><feature><location>../implementation_interface/rtf_format_i.xml#f_is_bold</location>is_bold</feature><symbol>:</symbol> <class><include>False</include>BOOLEAN</class>
			<comment>--</comment><comment> Is format bold?</comment>

	<anchor>f_is_italic</anchor><feature><location>../implementation_interface/rtf_format_i.xml#f_is_italic</location>is_italic</feature><symbol>:</symbol> <class><include>False</include>BOOLEAN</class>
			<comment>--</comment><comment> Is format italic?</comment>

	<anchor>f_is_striked_out</anchor><feature><location>../implementation_interface/rtf_format_i.xml#f_is_striked_out</location>is_striked_out</feature><symbol>:</symbol> <class><include>False</include>BOOLEAN</class>
			<comment>--</comment><comment> Is format striken out?</comment>

	<anchor>f_is_underlined</anchor><feature><location>../implementation_interface/rtf_format_i.xml#f_is_underlined</location>is_underlined</feature><symbol>:</symbol> <class><include>False</include>BOOLEAN</class>
			<comment>--</comment><comment> Is format underlined?</comment>

	<anchor>f_vertical_offset</anchor><feature><location>../implementation_interface/rtf_format_i.xml#f_vertical_offset</location>vertical_offset</feature><symbol>:</symbol> <class><include>False</include>INTEGER_32</class>
			<comment>--</comment><comment> Vertical offset in pixels.</comment>

	<anchor>f_font_height</anchor><feature><location>../implementation_interface/rtf_format_i.xml#f_font_height</location>font_height</feature><symbol>:</symbol> <class><include>False</include>INTEGER_32</class>
			<comment>--</comment><comment> Height of font used by format.</comment>

	<anchor>f_character_format</anchor><feature><location>../implementation_interface/rtf_format_i.xml#f_character_format</location>character_format</feature><symbol>:</symbol> <class><include>False</include>INTEGER_32</class>
			<comment>--</comment><comment> Current character format index.</comment>

	<anchor>f_boolean_out</anchor><feature><location>../implementation_interface/rtf_format_i.xml#f_boolean_out</location>boolean_out</feature> <symbol>(</symbol><local>a_boolean</local><symbol>:</symbol> <class><include>False</include>BOOLEAN</class><symbol>)</symbol><symbol>:</symbol> <class><include>False</include>STRING_8</class>
		<keyword>do</keyword>
			<keyword>if</keyword> <local>a_boolean</local> <keyword>then</keyword>
				<keyword>Result</keyword> <symbol>:=</symbol> <feature><location>../implementation_interface/rtf_format_i.xml#f_true_constant</location>True_constant</feature>
			<keyword>else</keyword>
				<keyword>Result</keyword> <symbol>:=</symbol> <feature><location>../implementation_interface/rtf_format_i.xml#f_false_constant</location>False_constant</feature>
			<keyword>end</keyword>
		<keyword>end</keyword>

	<anchor>f_true_constant</anchor><feature><location>../implementation_interface/rtf_format_i.xml#f_true_constant</location>True_constant</feature><symbol>:</symbol> <class><include>False</include>STRING_8</class> <symbol>=</symbol> &quot;T&quot;

	<anchor>f_false_constant</anchor><feature><location>../implementation_interface/rtf_format_i.xml#f_false_constant</location>False_constant</feature><symbol>:</symbol> <class><include>False</include>STRING_8</class> <symbol>=</symbol> &quot;F&quot;

	<anchor>f_character_format_out</anchor><feature><location>../implementation_interface/rtf_format_i.xml#f_character_format_out</location>character_format_out</feature><symbol>:</symbol> <class><include>False</include>STRING_8</class>
			<comment>--</comment><comment> Result is representation of character format attributes of </comment><quoted>Current</quoted><comment>.</comment>
			<comment>--</comment><comment> Paragraph and formats need to be buffered independently, hence a</comment>
			<comment>--</comment><comment> separate out feature for each of these set of attributes.</comment>
		<keyword>do</keyword>
			<keyword>if</keyword> <keyword>attached</keyword> <feature><location>../implementation_interface/rtf_format_i.xml#f_internal_character_format_out</location>internal_character_format_out</feature> <keyword>as</keyword> l_internal_character_format_out <keyword>then</keyword>
				<keyword>Result</keyword> <symbol>:=</symbol> <local>l_internal_character_format_out</local>
			<keyword>else</keyword>
				<keyword>create</keyword> <keyword>Result</keyword><dot>.</dot><feature><include>False</include>make</feature><symbol> </symbol><symbol>(</symbol><number>30</number><symbol>)</symbol>
				<keyword>Result</keyword><dot>.</dot><feature><include>False</include>append_integer</feature><symbol> </symbol><symbol>(</symbol><feature><location>../implementation_interface/rtf_format_i.xml#f_highlight_color</location>highlight_color</feature><symbol>)</symbol>
				<keyword>Result</keyword><dot>.</dot><feature><include>False</include>append</feature><symbol> </symbol><symbol>(</symbol><feature><location>../implementation_interface/rtf_format_i.xml#f_boolean_out</location>boolean_out</feature><symbol> </symbol><symbol>(</symbol><feature><location>../implementation_interface/rtf_format_i.xml#f_is_bold</location>is_bold</feature><symbol>)</symbol><symbol>)</symbol>
				<keyword>Result</keyword><dot>.</dot><feature><include>False</include>append_integer</feature><symbol> </symbol><symbol>(</symbol><feature><location>../implementation_interface/rtf_format_i.xml#f_character_format</location>character_format</feature><symbol>)</symbol>
				<keyword>Result</keyword><dot>.</dot><feature><include>False</include>append</feature><symbol> </symbol><symbol>(</symbol><feature><location>../implementation_interface/rtf_format_i.xml#f_boolean_out</location>boolean_out</feature><symbol> </symbol><symbol>(</symbol><feature><location>../implementation_interface/rtf_format_i.xml#f_is_italic</location>is_italic</feature><symbol>)</symbol><symbol>)</symbol>
				<keyword>Result</keyword><dot>.</dot><feature><include>False</include>append_integer</feature><symbol> </symbol><symbol>(</symbol><feature><location>../implementation_interface/rtf_format_i.xml#f_font_height</location>font_height</feature><symbol>)</symbol>
				<keyword>Result</keyword><dot>.</dot><feature><include>False</include>append</feature><symbol> </symbol><symbol>(</symbol><feature><location>../implementation_interface/rtf_format_i.xml#f_boolean_out</location>boolean_out</feature><symbol> </symbol><symbol>(</symbol><feature><location>../implementation_interface/rtf_format_i.xml#f_is_striked_out</location>is_striked_out</feature><symbol>)</symbol><symbol>)</symbol>
				<keyword>Result</keyword><dot>.</dot><feature><include>False</include>append_integer</feature><symbol> </symbol><symbol>(</symbol><feature><location>../implementation_interface/rtf_format_i.xml#f_text_color</location>text_color</feature><symbol>)</symbol>
				<keyword>Result</keyword><dot>.</dot><feature><include>False</include>append</feature><symbol> </symbol><symbol>(</symbol><feature><location>../implementation_interface/rtf_format_i.xml#f_boolean_out</location>boolean_out</feature><symbol> </symbol><symbol>(</symbol><feature><location>../implementation_interface/rtf_format_i.xml#f_is_underlined</location>is_underlined</feature><symbol>)</symbol><symbol>)</symbol>
				<keyword>Result</keyword><dot>.</dot><feature><include>False</include>append_integer</feature><symbol> </symbol><symbol>(</symbol><feature><location>../implementation_interface/rtf_format_i.xml#f_vertical_offset</location>vertical_offset</feature><symbol>)</symbol>
				<keyword>Result</keyword><dot>.</dot><feature><include>False</include>append</feature><symbol> </symbol><symbol>(</symbol><feature><location>../implementation_interface/rtf_format_i.xml#f_boolean_out</location>boolean_out</feature><symbol> </symbol><symbol>(</symbol><feature><location>../implementation_interface/rtf_format_i.xml#f_highlight_set</location>highlight_set</feature><symbol>)</symbol><symbol>)</symbol>
				<keyword>Result</keyword><dot>.</dot><feature><include>False</include>append</feature><symbol> </symbol><symbol>(</symbol><feature><location>../implementation_interface/rtf_format_i.xml#f_boolean_out</location>boolean_out</feature><symbol> </symbol><symbol>(</symbol><feature><location>../implementation_interface/rtf_format_i.xml#f_color_set</location>color_set</feature><symbol>)</symbol><symbol>)</symbol>
				<feature><location>../implementation_interface/rtf_format_i.xml#f_internal_character_format_out</location>internal_character_format_out</feature> <symbol>:=</symbol> <keyword>Result</keyword>
			<keyword>end</keyword>
		<keyword>end</keyword>
	
<keyword>feature</keyword> <comment>--</comment><comment> Access</comment>

	<anchor>f_alignment</anchor><feature><location>../implementation_interface/rtf_format_i.xml#f_alignment</location>alignment</feature><symbol>:</symbol> <class><include>False</include>INTEGER_32</class>
			<comment>--</comment><comment> Alignment of text.</comment>

	<anchor>f_bottom_spacing</anchor><feature><location>../implementation_interface/rtf_format_i.xml#f_bottom_spacing</location>bottom_spacing</feature><symbol>:</symbol> <class><include>False</include>INTEGER_32</class>
			<comment>--</comment><comment> Bottom spacing</comment>

	<anchor>f_top_spacing</anchor><feature><location>../implementation_interface/rtf_format_i.xml#f_top_spacing</location>top_spacing</feature><symbol>:</symbol> <class><include>False</include>INTEGER_32</class>
			<comment>--</comment><comment> Top spacing</comment>

	<anchor>f_right_margin</anchor><feature><location>../implementation_interface/rtf_format_i.xml#f_right_margin</location>right_margin</feature><symbol>:</symbol> <class><include>False</include>INTEGER_32</class>
			<comment>--</comment><comment> Right margin</comment>

	<anchor>f_left_margin</anchor><feature><location>../implementation_interface/rtf_format_i.xml#f_left_margin</location>left_margin</feature><symbol>:</symbol> <class><include>False</include>INTEGER_32</class>
			<comment>--</comment><comment> Left margin</comment>

	<anchor>f_reset_paragraph</anchor><feature><location>../implementation_interface/rtf_format_i.xml#f_reset_paragraph</location>reset_paragraph</feature>
			<comment>--</comment><comment> Ensure all paragraph formatting attributes are reset to</comment>
			<comment>--</comment><comment> default values.</comment>
		<keyword>do</keyword>
			<feature><location>../implementation_interface/rtf_format_i.xml#f_alignment</location>alignment</feature> <symbol>:=</symbol> <feature><location>../interface/ev_paragraph_constants.xml#f_alignment_left</location>Alignment_left</feature>
			<feature><location>../implementation_interface/rtf_format_i.xml#f_left_margin</location>left_margin</feature> <symbol>:=</symbol> <number>0</number>
			<feature><location>../implementation_interface/rtf_format_i.xml#f_right_margin</location>right_margin</feature> <symbol>:=</symbol> <number>0</number>
			<feature><location>../implementation_interface/rtf_format_i.xml#f_top_spacing</location>top_spacing</feature> <symbol>:=</symbol> <number>0</number>
			<feature><location>../implementation_interface/rtf_format_i.xml#f_bottom_spacing</location>bottom_spacing</feature> <symbol>:=</symbol> <number>0</number>
			<feature><location>../implementation_interface/rtf_format_i.xml#f_reset_internals</location>reset_internals</feature>
		<keyword>ensure</keyword>
				<feature><location>../implementation_interface/rtf_format_i.xml#f_alignment</location>alignment</feature> <symbol>=</symbol> <feature><location>../interface/ev_paragraph_constants.xml#f_alignment_left</location>Alignment_left</feature>
				<feature><location>../implementation_interface/rtf_format_i.xml#f_left_margin</location>left_margin</feature> <symbol>=</symbol> <number>0</number>
				<feature><location>../implementation_interface/rtf_format_i.xml#f_right_margin</location>right_margin</feature> <symbol>=</symbol> <number>0</number>
				<feature><location>../implementation_interface/rtf_format_i.xml#f_top_spacing</location>top_spacing</feature> <symbol>=</symbol> <number>0</number>
				<feature><location>../implementation_interface/rtf_format_i.xml#f_bottom_spacing</location>bottom_spacing</feature> <symbol>=</symbol> <number>0</number>
		<keyword>end</keyword>

	<anchor>f_paragraph_format_out</anchor><feature><location>../implementation_interface/rtf_format_i.xml#f_paragraph_format_out</location>paragraph_format_out</feature><symbol>:</symbol> <class><include>False</include>STRING_8</class>
			<comment>--</comment><comment> Result is representation of paragraph format attributes of </comment><quoted>Current</quoted><comment>.</comment>
			<comment>--</comment><comment> Paragraph and formats need to be buffered independently, hence a</comment>
			<comment>--</comment><comment> separate out fetaure for each of these set of attributes.</comment>
		<keyword>do</keyword>
			<keyword>if</keyword> <keyword>attached</keyword> <feature><location>../implementation_interface/rtf_format_i.xml#f_internal_paragraph_format_out</location>internal_paragraph_format_out</feature> <keyword>as</keyword> l_internal_paragraph_format_out <keyword>then</keyword>
				<keyword>Result</keyword> <symbol>:=</symbol> <local>l_internal_paragraph_format_out</local>
			<keyword>else</keyword>
				<keyword>create</keyword> <keyword>Result</keyword><dot>.</dot><feature><include>False</include>make</feature><symbol> </symbol><symbol>(</symbol><number>16</number><symbol>)</symbol>
				<keyword>Result</keyword><dot>.</dot><feature><include>False</include>append_integer</feature><symbol> </symbol><symbol>(</symbol><feature><location>../implementation_interface/rtf_format_i.xml#f_alignment</location>alignment</feature><symbol>)</symbol>
				<keyword>Result</keyword><dot>.</dot><feature><include>False</include>append_integer</feature><symbol> </symbol><symbol>(</symbol><feature><location>../implementation_interface/rtf_format_i.xml#f_bottom_spacing</location>bottom_spacing</feature><symbol>)</symbol>
				<keyword>Result</keyword><dot>.</dot><feature><include>False</include>append_integer</feature><symbol> </symbol><symbol>(</symbol><feature><location>../implementation_interface/rtf_format_i.xml#f_top_spacing</location>top_spacing</feature><symbol>)</symbol>
				<keyword>Result</keyword><dot>.</dot><feature><include>False</include>append_integer</feature><symbol> </symbol><symbol>(</symbol><feature><location>../implementation_interface/rtf_format_i.xml#f_right_margin</location>right_margin</feature><symbol>)</symbol>
				<keyword>Result</keyword><dot>.</dot><feature><include>False</include>append_integer</feature><symbol> </symbol><symbol>(</symbol><feature><location>../implementation_interface/rtf_format_i.xml#f_left_margin</location>left_margin</feature><symbol>)</symbol>
				<feature><location>../implementation_interface/rtf_format_i.xml#f_internal_paragraph_format_out</location>internal_paragraph_format_out</feature> <symbol>:=</symbol> <keyword>Result</keyword>
			<keyword>end</keyword>
		<keyword>end</keyword>
	
<keyword>feature</keyword> <comment>--</comment><comment> Element change</comment>

	<anchor>f_set_bottom_spacing</anchor><feature><location>../implementation_interface/rtf_format_i.xml#f_set_bottom_spacing</location>set_bottom_spacing</feature> <symbol>(</symbol><local>a_bottom_spacing</local><symbol>:</symbol> <class><include>False</include>INTEGER_32</class><symbol>)</symbol>
			<comment>--</comment><comment> Set </comment><feature><location>../implementation_interface/rtf_format_i.xml#f_bottom_spacing</location>bottom_spacing</feature><comment> to </comment><quoted>a_bottom_spacing</quoted><comment>.</comment>
		<keyword>require</keyword>
			<tag>a_bottom_spacing_non_negative</tag><symbol>:</symbol> <local>a_bottom_spacing</local> <symbol>&gt;=</symbol> <number>0</number>
		<keyword>do</keyword>
			<feature><location>../implementation_interface/rtf_format_i.xml#f_bottom_spacing</location>bottom_spacing</feature> <symbol>:=</symbol> <local>a_bottom_spacing</local>
			<feature><location>../implementation_interface/rtf_format_i.xml#f_reset_internals</location>reset_internals</feature>
		<keyword>ensure</keyword>
			<tag>bottom_spacing_assigned</tag><symbol>:</symbol> <feature><location>../implementation_interface/rtf_format_i.xml#f_bottom_spacing</location>bottom_spacing</feature> <symbol>=</symbol> <local>a_bottom_spacing</local>
		<keyword>end</keyword>

	<anchor>f_set_top_spacing</anchor><feature><location>../implementation_interface/rtf_format_i.xml#f_set_top_spacing</location>set_top_spacing</feature> <symbol>(</symbol><local>a_top_spacing</local><symbol>:</symbol> <class><include>False</include>INTEGER_32</class><symbol>)</symbol>
			<comment>--</comment><comment> Set </comment><feature><location>../implementation_interface/rtf_format_i.xml#f_top_spacing</location>top_spacing</feature><comment> to </comment><quoted>a_top_spacing</quoted><comment>.</comment>
		<keyword>require</keyword>
			<tag>a_top_spacing_non_negative</tag><symbol>:</symbol> <local>a_top_spacing</local> <symbol>&gt;=</symbol> <number>0</number>
		<keyword>do</keyword>
			<feature><location>../implementation_interface/rtf_format_i.xml#f_top_spacing</location>top_spacing</feature> <symbol>:=</symbol> <local>a_top_spacing</local>
			<feature><location>../implementation_interface/rtf_format_i.xml#f_reset_internals</location>reset_internals</feature>
		<keyword>ensure</keyword>
			<tag>top_spacing_assigned</tag><symbol>:</symbol> <feature><location>../implementation_interface/rtf_format_i.xml#f_top_spacing</location>top_spacing</feature> <symbol>=</symbol> <local>a_top_spacing</local>
		<keyword>end</keyword>

	<anchor>f_set_right_margin</anchor><feature><location>../implementation_interface/rtf_format_i.xml#f_set_right_margin</location>set_right_margin</feature> <symbol>(</symbol><local>a_right_margin</local><symbol>:</symbol> <class><include>False</include>INTEGER_32</class><symbol>)</symbol>
			<comment>--</comment><comment> Set </comment><feature><location>../implementation_interface/rtf_format_i.xml#f_right_margin</location>right_margin</feature><comment> to </comment><quoted>a_right_margin</quoted><comment>.</comment>
		<keyword>require</keyword>
			<tag>a_right_margin_non_negative</tag><symbol>:</symbol> <local>a_right_margin</local> <symbol>&gt;=</symbol> <number>0</number>
		<keyword>do</keyword>
			<feature><location>../implementation_interface/rtf_format_i.xml#f_right_margin</location>right_margin</feature> <symbol>:=</symbol> <local>a_right_margin</local>
			<feature><location>../implementation_interface/rtf_format_i.xml#f_reset_internals</location>reset_internals</feature>
		<keyword>ensure</keyword>
			<tag>right_margin_assigned</tag><symbol>:</symbol> <feature><location>../implementation_interface/rtf_format_i.xml#f_right_margin</location>right_margin</feature> <symbol>=</symbol> <local>a_right_margin</local>
		<keyword>end</keyword>

	<anchor>f_set_left_margin</anchor><feature><location>../implementation_interface/rtf_format_i.xml#f_set_left_margin</location>set_left_margin</feature> <symbol>(</symbol><local>a_left_margin</local><symbol>:</symbol> <class><include>False</include>INTEGER_32</class><symbol>)</symbol>
			<comment>--</comment><comment> Set </comment><feature><location>../implementation_interface/rtf_format_i.xml#f_left_margin</location>left_margin</feature><comment> to </comment><quoted>a_left_margin</quoted><comment>.</comment>
		<keyword>require</keyword>
			<tag>a_left_margin_non_negative</tag><symbol>:</symbol> <local>a_left_margin</local> <symbol>&gt;=</symbol> <number>0</number>
		<keyword>do</keyword>
			<feature><location>../implementation_interface/rtf_format_i.xml#f_left_margin</location>left_margin</feature> <symbol>:=</symbol> <local>a_left_margin</local>
			<feature><location>../implementation_interface/rtf_format_i.xml#f_reset_internals</location>reset_internals</feature>
		<keyword>ensure</keyword>
			<tag>left_margin_assigned</tag><symbol>:</symbol> <feature><location>../implementation_interface/rtf_format_i.xml#f_left_margin</location>left_margin</feature> <symbol>=</symbol> <local>a_left_margin</local>
		<keyword>end</keyword>

	<anchor>f_set_highlight_color</anchor><feature><location>../implementation_interface/rtf_format_i.xml#f_set_highlight_color</location>set_highlight_color</feature> <symbol>(</symbol><local>a_highlight_color</local><symbol>:</symbol> <class><include>False</include>INTEGER_32</class><symbol>)</symbol>
			<comment>--</comment><comment> Set </comment><feature><location>../implementation_interface/rtf_format_i.xml#f_highlight_color</location>highlight_color</feature><comment> to </comment><quoted>a_highlight_color</quoted><comment>.</comment>
		<keyword>require</keyword>
			<tag>a_highlight_color_non_negative</tag><symbol>:</symbol> <local>a_highlight_color</local> <symbol>&gt;=</symbol> <number>0</number>
		<keyword>do</keyword>
			<feature><location>../implementation_interface/rtf_format_i.xml#f_highlight_color</location>highlight_color</feature> <symbol>:=</symbol> <local>a_highlight_color</local>
			<feature><location>../implementation_interface/rtf_format_i.xml#f_highlight_set</location>highlight_set</feature> <symbol>:=</symbol> <keyword>True</keyword>
			<feature><location>../implementation_interface/rtf_format_i.xml#f_reset_internals</location>reset_internals</feature>
		<keyword>ensure</keyword>
			<tag>highlight_color_assigned</tag><symbol>:</symbol> <feature><location>../implementation_interface/rtf_format_i.xml#f_highlight_color</location>highlight_color</feature> <symbol>=</symbol> <local>a_highlight_color</local>
		<keyword>end</keyword>

	<anchor>f_set_text_color</anchor><feature><location>../implementation_interface/rtf_format_i.xml#f_set_text_color</location>set_text_color</feature> <symbol>(</symbol><local>a_text_color</local><symbol>:</symbol> <class><include>False</include>INTEGER_32</class><symbol>)</symbol>
			<comment>--</comment><comment> Set </comment><feature><location>../implementation_interface/rtf_format_i.xml#f_text_color</location>text_color</feature><comment> to </comment><quoted>a_text_color</quoted><comment>.</comment>
		<keyword>require</keyword>
			<tag>a_text_color_non_negative</tag><symbol>:</symbol> <local>a_text_color</local> <symbol>&gt;=</symbol> <number>0</number>
		<keyword>do</keyword>
			<feature><location>../implementation_interface/rtf_format_i.xml#f_text_color</location>text_color</feature> <symbol>:=</symbol> <local>a_text_color</local>
			<feature><location>../implementation_interface/rtf_format_i.xml#f_color_set</location>color_set</feature> <symbol>:=</symbol> <keyword>True</keyword>
			<feature><location>../implementation_interface/rtf_format_i.xml#f_reset_internals</location>reset_internals</feature>
		<keyword>ensure</keyword>
			<tag>text_color_assigned</tag><symbol>:</symbol> <feature><location>../implementation_interface/rtf_format_i.xml#f_text_color</location>text_color</feature> <symbol>=</symbol> <local>a_text_color</local>
		<keyword>end</keyword>

	<anchor>f_set_bold</anchor><feature><location>../implementation_interface/rtf_format_i.xml#f_set_bold</location>set_bold</feature> <symbol>(</symbol><local>a_is_bold</local><symbol>:</symbol> <class><include>False</include>BOOLEAN</class><symbol>)</symbol>
			<comment>--</comment><comment> Set </comment><feature><location>../implementation_interface/rtf_format_i.xml#f_is_bold</location>is_bold</feature><comment> to </comment><quoted>a_is_bold</quoted><comment>.</comment>
		<keyword>do</keyword>
			<feature><location>../implementation_interface/rtf_format_i.xml#f_is_bold</location>is_bold</feature> <symbol>:=</symbol> <local>a_is_bold</local>
			<feature><location>../implementation_interface/rtf_format_i.xml#f_reset_internals</location>reset_internals</feature>
		<keyword>ensure</keyword>
			<tag>is_bold_assigned</tag><symbol>:</symbol> <feature><location>../implementation_interface/rtf_format_i.xml#f_is_bold</location>is_bold</feature> <symbol>=</symbol> <local>a_is_bold</local>
		<keyword>end</keyword>

	<anchor>f_set_italic</anchor><feature><location>../implementation_interface/rtf_format_i.xml#f_set_italic</location>set_italic</feature> <symbol>(</symbol><local>an_is_italic</local><symbol>:</symbol> <class><include>False</include>BOOLEAN</class><symbol>)</symbol>
			<comment>--</comment><comment> Set </comment><feature><location>../implementation_interface/rtf_format_i.xml#f_is_italic</location>is_italic</feature><comment> to </comment><quoted>an_is_italic</quoted><comment>.</comment>
		<keyword>do</keyword>
			<feature><location>../implementation_interface/rtf_format_i.xml#f_is_italic</location>is_italic</feature> <symbol>:=</symbol> <local>an_is_italic</local>
			<feature><location>../implementation_interface/rtf_format_i.xml#f_reset_internals</location>reset_internals</feature>
		<keyword>ensure</keyword>
			<tag>is_italic_assigned</tag><symbol>:</symbol> <feature><location>../implementation_interface/rtf_format_i.xml#f_is_italic</location>is_italic</feature> <symbol>=</symbol> <local>an_is_italic</local>
		<keyword>end</keyword>

	<anchor>f_set_striked_out</anchor><feature><location>../implementation_interface/rtf_format_i.xml#f_set_striked_out</location>set_striked_out</feature> <symbol>(</symbol><local>an_is_striked_out</local><symbol>:</symbol> <class><include>False</include>BOOLEAN</class><symbol>)</symbol>
			<comment>--</comment><comment> Set </comment><feature><location>../implementation_interface/rtf_format_i.xml#f_is_striked_out</location>is_striked_out</feature><comment> to </comment><quoted>an_is_striked_out</quoted><comment>.</comment>
		<keyword>do</keyword>
			<feature><location>../implementation_interface/rtf_format_i.xml#f_is_striked_out</location>is_striked_out</feature> <symbol>:=</symbol> <local>an_is_striked_out</local>
			<feature><location>../implementation_interface/rtf_format_i.xml#f_reset_internals</location>reset_internals</feature>
		<keyword>ensure</keyword>
			<tag>is_striked_out_assigned</tag><symbol>:</symbol> <feature><location>../implementation_interface/rtf_format_i.xml#f_is_striked_out</location>is_striked_out</feature> <symbol>=</symbol> <local>an_is_striked_out</local>
		<keyword>end</keyword>

	<anchor>f_set_underlined</anchor><feature><location>../implementation_interface/rtf_format_i.xml#f_set_underlined</location>set_underlined</feature> <symbol>(</symbol><local>an_is_underlined</local><symbol>:</symbol> <class><include>False</include>BOOLEAN</class><symbol>)</symbol>
			<comment>--</comment><comment> Set </comment><feature><location>../implementation_interface/rtf_format_i.xml#f_is_underlined</location>is_underlined</feature><comment> to </comment><quoted>an_is_underlined</quoted><comment>.</comment>
		<keyword>do</keyword>
			<feature><location>../implementation_interface/rtf_format_i.xml#f_is_underlined</location>is_underlined</feature> <symbol>:=</symbol> <local>an_is_underlined</local>
			<feature><location>../implementation_interface/rtf_format_i.xml#f_reset_internals</location>reset_internals</feature>
		<keyword>ensure</keyword>
			<tag>is_underlined</tag><symbol>:</symbol> <feature><location>../implementation_interface/rtf_format_i.xml#f_is_underlined</location>is_underlined</feature> <symbol>=</symbol> <local>an_is_underlined</local>
		<keyword>end</keyword>

	<anchor>f_set_vertical_offset</anchor><feature><location>../implementation_interface/rtf_format_i.xml#f_set_vertical_offset</location>set_vertical_offset</feature> <symbol>(</symbol><local>an_offset</local><symbol>:</symbol> <class><include>False</include>INTEGER_32</class><symbol>)</symbol>
			<comment>--</comment><comment> Set </comment><feature><location>../implementation_interface/rtf_format_i.xml#f_vertical_offset</location>vertical_offset</feature><comment> to </comment><quoted>an_offset</quoted><comment>.</comment>
		<keyword>do</keyword>
			<feature><location>../implementation_interface/rtf_format_i.xml#f_vertical_offset</location>vertical_offset</feature> <symbol>:=</symbol> <local>an_offset</local>
			<feature><location>../implementation_interface/rtf_format_i.xml#f_reset_internals</location>reset_internals</feature>
		<keyword>ensure</keyword>
			<tag>offset_set</tag><symbol>:</symbol> <feature><location>../implementation_interface/rtf_format_i.xml#f_vertical_offset</location>vertical_offset</feature> <symbol>=</symbol> <local>an_offset</local>
		<keyword>end</keyword>

	<anchor>f_set_font_height</anchor><feature><location>../implementation_interface/rtf_format_i.xml#f_set_font_height</location>set_font_height</feature> <symbol>(</symbol><local>a_font_height</local><symbol>:</symbol> <class><include>False</include>INTEGER_32</class><symbol>)</symbol>
			<comment>--</comment><comment> Set </comment><feature><location>../implementation_interface/rtf_format_i.xml#f_font_height</location>font_height</feature><comment> to </comment><quoted>a_font_height</quoted><comment>.</comment>
		<keyword>require</keyword>
			<tag>a_font_height_positive</tag><symbol>:</symbol> <local>a_font_height</local> <symbol>&gt;</symbol> <number>0</number>
		<keyword>do</keyword>
			<feature><location>../implementation_interface/rtf_format_i.xml#f_font_height</location>font_height</feature> <symbol>:=</symbol> <local>a_font_height</local>
			<feature><location>../implementation_interface/rtf_format_i.xml#f_reset_internals</location>reset_internals</feature>
		<keyword>ensure</keyword>
			<tag>font_height_assigned</tag><symbol>:</symbol> <feature><location>../implementation_interface/rtf_format_i.xml#f_font_height</location>font_height</feature> <symbol>=</symbol> <local>a_font_height</local>
		<keyword>end</keyword>

	<anchor>f_set_character_format</anchor><feature><location>../implementation_interface/rtf_format_i.xml#f_set_character_format</location>set_character_format</feature> <symbol>(</symbol><local>a_character_format</local><symbol>:</symbol> <class><include>False</include>INTEGER_32</class><symbol>)</symbol>
			<comment>--</comment><comment> Set </comment><feature><location>../implementation_interface/rtf_format_i.xml#f_character_format</location>character_format</feature><comment> to </comment><quoted>a_character_format</quoted><comment>.</comment>
		<keyword>require</keyword>
			<tag>a_character_format_non_negative</tag><symbol>:</symbol> <local>a_character_format</local> <symbol>&gt;=</symbol> <number>0</number>
		<keyword>do</keyword>
			<feature><location>../implementation_interface/rtf_format_i.xml#f_character_format</location>character_format</feature> <symbol>:=</symbol> <local>a_character_format</local>
			<feature><location>../implementation_interface/rtf_format_i.xml#f_reset_internals</location>reset_internals</feature>
		<keyword>ensure</keyword>
			<tag>character_format_assigned</tag><symbol>:</symbol> <feature><location>../implementation_interface/rtf_format_i.xml#f_character_format</location>character_format</feature> <symbol>=</symbol> <local>a_character_format</local>
		<keyword>end</keyword>

	<anchor>f_set_alignment</anchor><feature><location>../implementation_interface/rtf_format_i.xml#f_set_alignment</location>set_alignment</feature> <symbol>(</symbol><local>an_alignment</local><symbol>:</symbol> <class><include>False</include>INTEGER_32</class><symbol>)</symbol>
			<comment>--</comment><comment> Set </comment><feature><location>../implementation_interface/rtf_format_i.xml#f_alignment</location>alignment</feature><comment> to </comment><quoted>an_alignment</quoted><comment>.</comment>
		<keyword>require</keyword>
			<tag>valid_alignment</tag><symbol>:</symbol> <feature><location>../interface/ev_paragraph_constants.xml#f_valid_alignment</location>valid_alignment</feature><symbol> </symbol><symbol>(</symbol><local>an_alignment</local><symbol>)</symbol>
		<keyword>do</keyword>
			<feature><location>../implementation_interface/rtf_format_i.xml#f_alignment</location>alignment</feature> <symbol>:=</symbol> <local>an_alignment</local>
			<feature><location>../implementation_interface/rtf_format_i.xml#f_reset_internals</location>reset_internals</feature>
		<keyword>ensure</keyword>
			<tag>alignment_set</tag><symbol>:</symbol> <feature><location>../implementation_interface/rtf_format_i.xml#f_alignment</location>alignment</feature> <symbol>=</symbol> <local>an_alignment</local>
		<keyword>end</keyword>
	
<keyword>feature</keyword> <symbol>{</symbol>NONE<symbol>}</symbol> <comment>--</comment><comment> Implementation</comment>

	<anchor>f_internal_character_format_out</anchor><feature><location>../implementation_interface/rtf_format_i.xml#f_internal_character_format_out</location>internal_character_format_out</feature><symbol>:</symbol> <keyword>detachable</keyword> <class><include>False</include>STRING_8</class>
			<comment>--</comment><comment> Once per object for </comment><feature><location>../implementation_interface/rtf_format_i.xml#f_character_format_out</location>character_format_out</feature><comment>.</comment>

	<anchor>f_internal_paragraph_format_out</anchor><feature><location>../implementation_interface/rtf_format_i.xml#f_internal_paragraph_format_out</location>internal_paragraph_format_out</feature><symbol>:</symbol> <keyword>detachable</keyword> <class><include>False</include>STRING_8</class>
			<comment>--</comment><comment> Once per object for </comment><feature><location>../implementation_interface/rtf_format_i.xml#f_paragraph_format_out</location>paragraph_format_out</feature><comment>.</comment>

	<anchor>f_reset_internals</anchor><feature><location>../implementation_interface/rtf_format_i.xml#f_reset_internals</location>reset_internals</feature>
			<comment>--</comment><comment> Reset </comment><feature><location>../implementation_interface/rtf_format_i.xml#f_internal_character_format_out</location>internal_character_format_out</feature><comment>.</comment>
		<keyword>do</keyword>
			<feature><location>../implementation_interface/rtf_format_i.xml#f_internal_character_format_out</location>internal_character_format_out</feature> <symbol>:=</symbol> <keyword>Void</keyword>
			<feature><location>../implementation_interface/rtf_format_i.xml#f_internal_paragraph_format_out</location>internal_paragraph_format_out</feature> <symbol>:=</symbol> <keyword>Void</keyword>
		<keyword>ensure</keyword>
			<tag>internal_character_format_out_reset</tag><symbol>:</symbol> <feature><location>../implementation_interface/rtf_format_i.xml#f_internal_character_format_out</location>internal_character_format_out</feature> <symbol>=</symbol> <keyword>Void</keyword>
		<keyword>end</keyword>
	
<keyword>invariant</keyword>
	<tag>character_format_non_negative</tag><symbol>:</symbol> <feature><location>../implementation_interface/rtf_format_i.xml#f_character_format</location>character_format</feature> <symbol>&gt;=</symbol> <number>0</number>
	<tag>font_height_non_negative</tag><symbol>:</symbol> <feature><location>../implementation_interface/rtf_format_i.xml#f_font_height</location>font_height</feature> <symbol>&gt;=</symbol> <number>0</number>
	<tag>text_color_non_negative</tag><symbol>:</symbol> <feature><location>../implementation_interface/rtf_format_i.xml#f_text_color</location>text_color</feature> <symbol>&gt;=</symbol> <number>0</number>
	<tag>highlight_color_non_negative</tag><symbol>:</symbol> <feature><location>../implementation_interface/rtf_format_i.xml#f_highlight_color</location>highlight_color</feature> <symbol>&gt;=</symbol> <number>0</number>
	<tag>left_margin_non_negative</tag><symbol>:</symbol> <feature><location>../implementation_interface/rtf_format_i.xml#f_left_margin</location>left_margin</feature> <symbol>&gt;=</symbol> <number>0</number>
	<tag>right_margin_non_negative</tag><symbol>:</symbol> <feature><location>../implementation_interface/rtf_format_i.xml#f_right_margin</location>right_margin</feature> <symbol>&gt;=</symbol> <number>0</number>
	<tag>top_spacing_non_negative</tag><symbol>:</symbol> <feature><location>../implementation_interface/rtf_format_i.xml#f_top_spacing</location>top_spacing</feature> <symbol>&gt;=</symbol> <number>0</number>
	<tag>bottom_spacing_non_negative</tag><symbol>:</symbol> <feature><location>../implementation_interface/rtf_format_i.xml#f_bottom_spacing</location>bottom_spacing</feature> <symbol>&gt;=</symbol> <number>0</number>

<keyword>note</keyword>
	<indexing_tag>copyright</indexing_tag><symbol>:</symbol> <string>&quot;Copyright (c) 1984-2006, Eiffel Software and others&quot;</string>
	<indexing_tag>license</indexing_tag><symbol>:</symbol> <string>&quot;Eiffel Forum License v2 (see </string><string><location>http://www.eiffel.com/licensing/forum.txt</location>http://www.eiffel.com/licensing/forum.txt</string><string>)&quot;</string>
	<indexing_tag>source</indexing_tag><symbol>:</symbol> <string>&quot;</string><string>[</string>
		<string>Eiffel Software</string>
		<string>356 Storke Road, Goleta, CA 93117 USA</string>
		<string>Telephone 805-685-1006, Fax 805-685-6869</string>
		<string>Website </string><string><location>http://www.eiffel.com</location>http://www.eiffel.com</string>
		<string>Customer support </string><string><location>http://support.eiffel.com</location>http://support.eiffel.com</string>
	<string>]</string><string>&quot;</string>

<keyword>end</keyword> <comment>--</comment> <comment>class </comment><class><location>../implementation_interface/rtf_format_i.xml</location>RTF_FORMAT_I</class></system>

