<system>
<keyword>note</keyword>
	<indexing_tag>description</indexing_tag><symbol>:</symbol> <string>&quot;</string><string>[</string>
		<string>Row item for use in EV_MULTI_COLUMN_LIST</string>
	<string>]</string><string>&quot;</string>
	<indexing_tag>legal</indexing_tag><symbol>:</symbol> <string>&quot;See notice at end of class.&quot;</string>
	<indexing_tag>status</indexing_tag><symbol>:</symbol> <string>&quot;See notice at end of class.&quot;</string>
	<indexing_tag>keywords</indexing_tag><symbol>:</symbol> <string>&quot;multi column list, row, item, select&quot;</string>
	<indexing_tag>date</indexing_tag><symbol>:</symbol> <string>&quot;$Date: 2017-05-03 08:56:14 -0700 (Wed, 03 May 2017) $&quot;</string>
	<indexing_tag>revision</indexing_tag><symbol>:</symbol> <string>&quot;$Revision: 100317 $&quot;</string>

<keyword>class</keyword> 
	<class><location>../interface/ev_multi_column_list_row.xml</location>EV_MULTI_COLUMN_LIST_ROW</class>

<keyword>inherit</keyword>
	<class><location>../interface/ev_item.xml</location>EV_ITEM</class>
		<keyword>undefine</keyword>
			<feature><include>False</include>copy</feature><symbol>,</symbol>
			<feature><include>False</include>is_equal</feature>
		<keyword>redefine</keyword>
			<feature><location>../interface/ev_multi_column_list_row.xml#f_implementation</location>implementation</feature><symbol>,</symbol>
			<feature><location>../interface/ev_multi_column_list_row.xml#f_is_in_default_state</location>is_in_default_state</feature>
		<keyword>select</keyword>
			<feature><location>../interface/ev_any.xml#f_default_create</location>default_create</feature>
		<keyword>end</keyword>

	<class><include>False</include>INTERACTIVE_LIST</class> <symbol>[</symbol><class><include>False</include>STRING_32</class><symbol>]</symbol>
		<keyword>rename</keyword>
			<feature><include>False</include>default_create</feature> <keyword>as</keyword> <feature><include>False</include>interactive_list_make</feature>
		<keyword>redefine</keyword>
			<feature><location>../interface/ev_multi_column_list_row.xml#f_on_item_added_at</location>on_item_added_at</feature><symbol>,</symbol>
			<feature><location>../interface/ev_multi_column_list_row.xml#f_on_item_removed_at</location>on_item_removed_at</feature><symbol>,</symbol>
			<feature><location>../interface/ev_multi_column_list_row.xml#f_make_filled</location>make_filled</feature>
		<keyword>end</keyword>

	<class><location>../interface/ev_deselectable.xml</location>EV_DESELECTABLE</class>
		<keyword>undefine</keyword>
			<feature><location>../interface/ev_any.xml#f_initialize</location>initialize</feature><symbol>,</symbol>
			<feature><include>False</include>copy</feature><symbol>,</symbol>
			<feature><include>False</include>is_equal</feature>
		<keyword>redefine</keyword>
			<feature><location>../interface/ev_multi_column_list_row.xml#f_implementation</location>implementation</feature><symbol>,</symbol>
			<feature><location>../interface/ev_multi_column_list_row.xml#f_is_in_default_state</location>is_in_default_state</feature>
		<keyword>end</keyword>

	<class><location>../interface/ev_multi_column_list_row_action_sequences.xml</location>EV_MULTI_COLUMN_LIST_ROW_ACTION_SEQUENCES</class>

<keyword>create</keyword> 
	<feature><location>../interface/ev_any.xml#f_default_create</location>default_create</feature>


<keyword>create</keyword> <symbol>{</symbol><class><location>../interface/ev_multi_column_list_row.xml</location>EV_MULTI_COLUMN_LIST_ROW</class><symbol>}</symbol>
	<feature><location>../interface/ev_multi_column_list_row.xml#f_make_filled</location>make_filled</feature>

<keyword>feature</keyword> <symbol>{</symbol>NONE<symbol>}</symbol> <comment>--</comment><comment> Initialization</comment>

	<anchor>f_make_filled</anchor><feature><location>../interface/ev_multi_column_list_row.xml#f_make_filled</location>make_filled</feature> <symbol>(</symbol><local>n</local><symbol>:</symbol> <class><include>False</include>INTEGER_32</class><symbol>)</symbol>
			<comment>--</comment><comment> Allocate list with </comment><quoted>n</quoted><comment> items.</comment>
			<comment>--</comment><comment> (</comment><quoted>n</quoted><comment> may be zero for empty list.)</comment>
			<comment>--</comment><comment> This list will be full.</comment>
		<keyword>do</keyword>
			<feature><location>../interface/ev_any.xml#f_default_create</location>default_create</feature>
			<keyword><location>file#f_feature</location>Precursor</keyword><symbol> </symbol><symbol>(</symbol><local>n</local><symbol>)</symbol>
		<keyword>end</keyword>
	
<keyword>feature</keyword> <symbol>{</symbol>NONE<symbol>}</symbol> <comment>--</comment><comment> Contract support</comment>

	<anchor>f_is_in_default_state</anchor><feature><location>../interface/ev_multi_column_list_row.xml#f_is_in_default_state</location>is_in_default_state</feature><symbol>:</symbol> <class><include>False</include>BOOLEAN</class>
			<comment>--</comment><comment> Is </comment><quoted>Current</quoted><comment> in its default state?</comment>
		<keyword>do</keyword>
			<keyword>Result</keyword> <symbol>:=</symbol> <keyword><location>../interface/ev_item.xml#f_is_in_default_state</location>Precursor</keyword> <symbol>{</symbol><class><location>../interface/ev_item.xml</location>EV_ITEM</class><symbol>}</symbol> <keyword>and</keyword> <keyword><location>../interface/ev_deselectable.xml#f_is_in_default_state</location>Precursor</keyword> <symbol>{</symbol><class><location>../interface/ev_deselectable.xml</location>EV_DESELECTABLE</class><symbol>}</symbol>
		<keyword>end</keyword>
	
<keyword>feature</keyword> <comment>--</comment><comment> Element change</comment>

	<anchor>f_fill_with_strings_8</anchor><feature><location>../interface/ev_multi_column_list_row.xml#f_fill_with_strings_8</location>fill_with_strings_8</feature> <symbol>(</symbol><local>other</local><symbol>:</symbol> <class><include>False</include>CONTAINER</class> <symbol>[</symbol><class><include>False</include>STRING_8</class><symbol>]</symbol><symbol>)</symbol>
		<keyword>obsolete</keyword> &quot;Use `fill' for Unicode support. [2017-05-31]&quot;
			<comment>--</comment><comment> Fill with as many items of </comment><quoted>other</quoted><comment> as possible.</comment>
			<comment>--</comment><comment> The representations of </comment><quoted>other</quoted><comment> and current structure</comment>
			<comment>--</comment><comment> need not be the same.</comment>
		<keyword>local</keyword>
			<local>lin_rep</local><symbol>:</symbol> <class><include>False</include>LINEAR</class> <symbol>[</symbol><class><include>False</include>STRING_8</class><symbol>]</symbol>
			<local>l_cursor</local><symbol>:</symbol> <class><include>False</include>CURSOR</class>
		<keyword>do</keyword>
			<local>lin_rep</local> <symbol>:=</symbol> <local>other</local><dot>.</dot><feature><include>False</include>linear_representation</feature>
			<keyword>from</keyword>
				<local>l_cursor</local> <symbol>:=</symbol> <feature><include>False</include>cursor</feature>
				<local>lin_rep</local><dot>.</dot><feature><include>False</include>start</feature>
			<keyword>until</keyword>
				<keyword>not</keyword> <feature><include>False</include>extendible</feature> <keyword>or else</keyword> <local>lin_rep</local><dot>.</dot><feature><include>False</include>off</feature>
			<keyword>loop</keyword>
				<feature><include>False</include>extend</feature><symbol> </symbol><symbol>(</symbol><local>lin_rep</local><dot>.</dot><feature><include>False</include>item</feature><dot>.</dot><feature><include>False</include>as_string_32_conversion</feature><symbol>)</symbol>
				<feature><include>False</include>finish</feature>
				<local>lin_rep</local><dot>.</dot><feature><include>False</include>forth</feature>
			<keyword>end</keyword>
			<feature><include>False</include>go_to</feature><symbol> </symbol><symbol>(</symbol><local>l_cursor</local><symbol>)</symbol>
		<keyword>end</keyword>
	
<keyword>feature</keyword> <symbol>{</symbol><class><location>../interface/ev_any.xml</location>EV_ANY</class><symbol>,</symbol> <class><location>../implementation_interface/ev_any_i.xml</location>EV_ANY_I</class><symbol>}</symbol> <comment>--</comment><comment> Implementation</comment>

	<anchor>f_implementation</anchor><feature><location>../interface/ev_multi_column_list_row.xml#f_implementation</location>implementation</feature><symbol>:</symbol> <class><location>../implementation_interface/ev_multi_column_list_row_i.xml</location>EV_MULTI_COLUMN_LIST_ROW_I</class>
			<comment>--</comment><comment> Responsible for interaction with native graphics toolkit.</comment>
	
<keyword>feature</keyword> <symbol>{</symbol><class><location>../implementation_interface/ev_any_i.xml</location>EV_ANY_I</class><symbol>}</symbol> <comment>--</comment><comment> Implementation</comment>

	<anchor>f_on_item_added_at</anchor><feature><location>../interface/ev_multi_column_list_row.xml#f_on_item_added_at</location>on_item_added_at</feature> <symbol>(</symbol><local>an_item</local><symbol>:</symbol> <keyword>like</keyword> <feature><include>False</include>item</feature><symbol>;</symbol> <local>item_index</local><symbol>:</symbol> <class><include>False</include>INTEGER_32</class><symbol>)</symbol>
			<comment>--</comment><comment> </comment><quoted>an_item</quoted><comment> is about to be added.</comment>
		<keyword>do</keyword>
			<feature><location>../interface/ev_multi_column_list_row.xml#f_implementation</location>implementation</feature><dot>.</dot><feature><location>../implementation_interface/ev_multi_column_list_row_i.xml#f_on_item_added_at</location>on_item_added_at</feature><symbol> </symbol><symbol>(</symbol><local>an_item</local><symbol>,</symbol> <local>item_index</local><symbol>)</symbol>
		<keyword>end</keyword>

	<anchor>f_on_item_removed_at</anchor><feature><location>../interface/ev_multi_column_list_row.xml#f_on_item_removed_at</location>on_item_removed_at</feature> <symbol>(</symbol><local>an_item</local><symbol>:</symbol> <keyword>like</keyword> <feature><include>False</include>item</feature><symbol>;</symbol> <local>item_index</local><symbol>:</symbol> <class><include>False</include>INTEGER_32</class><symbol>)</symbol>
			<comment>--</comment><comment> </comment><quoted>an_item</quoted><comment> is about to be removed.</comment>
		<keyword>do</keyword>
			<feature><location>../interface/ev_multi_column_list_row.xml#f_implementation</location>implementation</feature><dot>.</dot><feature><location>../implementation_interface/ev_multi_column_list_row_i.xml#f_on_item_removed_at</location>on_item_removed_at</feature><symbol> </symbol><symbol>(</symbol><local>an_item</local><symbol>,</symbol> <local>item_index</local><symbol>)</symbol>
		<keyword>end</keyword>
	
<keyword>feature</keyword> <symbol>{</symbol>NONE<symbol>}</symbol> <comment>--</comment><comment> Implementation</comment>

	<anchor>f_create_implementation</anchor><feature><location>../interface/ev_multi_column_list_row.xml#f_create_implementation</location>create_implementation</feature>
			<comment>--</comment><comment> See </comment><quoted>{EV_ANY}.create_implementation</quoted><comment>.</comment>
		<keyword>do</keyword>
			<keyword>create</keyword> <symbol>{</symbol><class><location>../implementation_gtk/ev_multi_column_list_row_imp.xml</location>EV_MULTI_COLUMN_LIST_ROW_IMP</class><symbol>}</symbol> <feature><location>../interface/ev_multi_column_list_row.xml#f_implementation</location>implementation</feature><dot>.</dot><feature><location>../implementation_gtk/ev_multi_column_list_row_imp.xml#f_make</location>make</feature>
			<feature><include>False</include>interactive_list_make</feature>
		<keyword>end</keyword>

	<anchor>f_new_filled_list</anchor><feature><location>../interface/ev_multi_column_list_row.xml#f_new_filled_list</location>new_filled_list</feature> <symbol>(</symbol><local>n</local><symbol>:</symbol> <class><include>False</include>INTEGER_32</class><symbol>)</symbol><symbol>:</symbol> <keyword>like</keyword> <keyword>Current</keyword>
			<comment>--</comment><comment> New list with </comment><quoted>n</quoted><comment> elements.</comment>
		<keyword>do</keyword>
			<keyword>create</keyword> <keyword>Result</keyword><dot>.</dot><feature><location>../interface/ev_multi_column_list_row.xml#f_make_filled</location>make_filled</feature><symbol> </symbol><symbol>(</symbol><local>n</local><symbol>)</symbol>
		<keyword>end</keyword>
	
<keyword>note</keyword>
	<indexing_tag>copyright</indexing_tag><symbol>:</symbol> <string>&quot;Copyright (c) 1984-2016, Eiffel Software and others&quot;</string>
	<indexing_tag>license</indexing_tag><symbol>:</symbol> <string>&quot;Eiffel Forum License v2 (see </string><string><location>http://www.eiffel.com/licensing/forum.txt</location>http://www.eiffel.com/licensing/forum.txt</string><string>)&quot;</string>
	<indexing_tag>source</indexing_tag><symbol>:</symbol> <string>&quot;</string><string>[</string>
		<string>Eiffel Software</string>
		<string>5949 Hollister Ave., Goleta, CA 93117 USA</string>
		<string>Telephone 805-685-1006, Fax 805-685-6869</string>
		<string>Website </string><string><location>http://www.eiffel.com</location>http://www.eiffel.com</string>
		<string>Customer support </string><string><location>http://support.eiffel.com</location>http://support.eiffel.com</string>
	<string>]</string><string>&quot;</string>

<keyword>end</keyword> <comment>--</comment> <comment>class </comment><class><location>../interface/ev_multi_column_list_row.xml</location>EV_MULTI_COLUMN_LIST_ROW</class></system>

