<system>
<keyword>deferred</keyword> <keyword>class</keyword>
	<class><location>../implementation_gtk/ev_gauge_imp_links.xml</location>EV_GAUGE_IMP</class>

<keyword>Ancestors</keyword>
	<class><location>../implementation_interface/ev_gauge_i_links.xml</location>EV_GAUGE_I</class><char>*</char>
	<class><location>../implementation_gtk/ev_primitive_imp_links.xml</location>EV_PRIMITIVE_IMP</class><char>*</char>

<keyword>Clients</keyword>
	<class><location>../implementation_gtk/ev_gauge_imp_links.xml</location>EV_GAUGE_IMP</class><char>*</char>
	<class><location>../implementation_gtk/ev_intermediary_routines_links.xml</location>EV_INTERMEDIARY_ROUTINES</class>

<keyword>Suppliers</keyword>
	<class><include>False</include>ACTION_SEQUENCE</class> <symbol>[</symbol><generic>EVENT_DATA</generic> <symbol>-&gt;</symbol> <keyword>detachable</keyword> <class><include>False</include>TUPLE</class> <keyword>create</keyword> <feature><include>False</include>default_create</feature> <keyword>end</keyword><symbol>]</symbol>
	<class><include>False</include>ACTIVE_INTEGER_INTERVAL</class>
	<class><location>../implementation_gtk/ev_application_imp_links.xml</location>EV_APPLICATION_IMP</class>
	<class><location>../implementation_gtk/ev_gauge_imp_links.xml</location>EV_GAUGE_IMP</class><char>*</char>
	<class><location>../implementation_gtk/ev_gtk_callback_marshal_links.xml</location>EV_GTK_CALLBACK_MARSHAL</class>
	<class><location>../implementation_gtk/ev_primitive_imp_links.xml</location>EV_PRIMITIVE_IMP</class><char>*</char>
	<class><location>../interface/ev_value_change_action_sequence_links.xml</location>EV_VALUE_CHANGE_ACTION_SEQUENCE</class>
	<class><location>../implementation_gtk/gtk_links.xml</location>GTK</class>
	<class><location>../implementation_gtk/gtk2_links.xml</location>GTK2</class>
	<class><include>False</include>INTEGER_32</class>
	<class><include>False</include>REAL_32</class>

</system>
