<system>
<keyword>note</keyword>
	<indexing_tag>description</indexing_tag><symbol>:</symbol> <string>&quot;EiffelVision label, gtk implementation.&quot;</string>
	<indexing_tag>legal</indexing_tag><symbol>:</symbol> <string>&quot;See notice at end of class.&quot;</string>
	<indexing_tag>status</indexing_tag><symbol>:</symbol> <string>&quot;See notice at end of class.&quot;</string>
	<indexing_tag>id</indexing_tag><symbol>:</symbol> <string>&quot;$Id: ev_label_imp.e 100058 2017-03-27 20:31:29Z jfiat $&quot;</string>
	<indexing_tag>date</indexing_tag><symbol>:</symbol> <string>&quot;$Date: 2017-03-27 13:31:29 -0700 (Mon, 27 Mar 2017) $&quot;</string>
	<indexing_tag>revision</indexing_tag><symbol>:</symbol> <string>&quot;$Revision: 100058 $&quot;</string>

<keyword>class</keyword> 
	<class><location>../implementation_gtk/ev_label_imp.xml</location>EV_LABEL_IMP</class>

<keyword>inherit</keyword>
	<class><location>../implementation_interface/ev_label_i.xml</location>EV_LABEL_I</class>
		<keyword>redefine</keyword>
			<feature><location>../implementation_gtk/ev_label_imp.xml#f_interface</location>interface</feature>
		<keyword>end</keyword>

	<class><location>../implementation_gtk/ev_primitive_imp.xml</location>EV_PRIMITIVE_IMP</class>
		<keyword>redefine</keyword>
			<feature><location>../implementation_gtk/ev_label_imp.xml#f_interface</location>interface</feature><symbol>,</symbol>
			<feature><location>../implementation_gtk/ev_label_imp.xml#f_needs_event_box</location>Needs_event_box</feature><symbol>,</symbol>
			<feature><location>../implementation_gtk/ev_label_imp.xml#f_make</location>make</feature>
		<keyword>end</keyword>

	<class><location>../implementation_gtk/ev_textable_imp.xml</location>EV_TEXTABLE_IMP</class>
		<keyword>redefine</keyword>
			<feature><location>../implementation_gtk/ev_label_imp.xml#f_interface</location>interface</feature>
		<keyword>end</keyword>

	<class><location>../implementation_gtk/ev_fontable_imp.xml</location>EV_FONTABLE_IMP</class>
		<keyword>redefine</keyword>
			<feature><location>../implementation_gtk/ev_label_imp.xml#f_interface</location>interface</feature>
		<keyword>end</keyword>

<keyword>create</keyword> 
	<feature><location>../implementation_gtk/ev_label_imp.xml#f_make</location>make</feature>

<keyword>feature</keyword> <symbol>{</symbol>NONE<symbol>}</symbol> <comment>--</comment><comment> Initialization</comment>

	<anchor>f_old_make</anchor><feature><location>../implementation_gtk/ev_label_imp.xml#f_old_make</location>old_make</feature> <symbol>(</symbol><local>an_interface</local><symbol>:</symbol> <keyword>attached</keyword> <keyword>like</keyword> <feature><location>../implementation_gtk/ev_label_imp.xml#f_interface</location>interface</feature><symbol>)</symbol>
			<comment>--</comment><comment> Create a gtk label.</comment>
		<keyword>do</keyword>
			<feature><location>../implementation_interface/ev_any_i.xml#f_assign_interface</location>assign_interface</feature><symbol> </symbol><symbol>(</symbol><local>an_interface</local><symbol>)</symbol>
		<keyword>end</keyword>

	<anchor>f_make</anchor><feature><location>../implementation_gtk/ev_label_imp.xml#f_make</location>make</feature>
			<comment>--</comment><comment> Create and initialize label.</comment>
		<keyword>local</keyword>
			<local>a_cs</local><symbol>:</symbol> <class><location>../implementation_gtk/ev_gtk_c_string.xml</location>EV_GTK_C_STRING</class>
			<local>int_value</local><symbol>:</symbol> <class><include>False</include>INTEGER_32</class>
		<keyword>do</keyword>
			<feature><location>../implementation_gtk/ev_textable_imp.xml#f_textable_imp_initialize</location>textable_imp_initialize</feature>
			<feature><location>../implementation_gtk/ev_any_imp.xml#f_set_c_object</location>set_c_object</feature><symbol> </symbol><symbol>(</symbol><feature><location>../implementation_gtk/ev_textable_imp.xml#f_text_label</location>text_label</feature><symbol>)</symbol>
			<feature><location>../implementation_gtk/ev_textable_imp.xml#f_align_text_center</location>align_text_center</feature>
			<local>a_cs</local> <symbol>:=</symbol> <feature><location>../implementation_gtk/ev_any_imp.xml#f_app_implementation</location>App_implementation</feature><dot>.</dot><feature><location>../implementation_gtk/ev_application_imp.xml#f_c_string_from_eiffel_string</location>c_string_from_eiffel_string</feature><symbol> </symbol><symbol>(</symbol><keyword>once</keyword> &quot;justify&quot;<symbol>)</symbol>
			<symbol>{</symbol><class><location>../implementation_gtk/gtk2.xml</location>GTK2</class><symbol>}</symbol><dot>.</dot><feature><location>../implementation_gtk/gtk2.xml#f_g_object_get_integer</location>g_object_get_integer</feature> <symbol>(</symbol><feature><location>../implementation_gtk/ev_textable_imp.xml#f_text_label</location>text_label</feature><symbol>,</symbol> <local>a_cs</local><dot>.</dot><feature><location>../implementation_gtk/ev_gtk_c_string.xml#f_item</location>item</feature><symbol>,</symbol> <symbol>$</symbol><local>int_value</local><symbol>)</symbol>
			<keyword><location>../implementation_gtk/ev_primitive_imp.xml#f_make</location>Precursor</keyword>
			<feature><location>../implementation_interface/ev_any_i.xml#f_set_is_initialized</location>set_is_initialized</feature><symbol> </symbol><symbol>(</symbol><keyword>True</keyword><symbol>)</symbol>
		<keyword>end</keyword>
	
<keyword>feature</keyword> <comment>--</comment><comment> Access</comment>

	<anchor>f_angle</anchor><feature><location>../implementation_gtk/ev_label_imp.xml#f_angle</location>angle</feature><symbol>:</symbol> <class><include>False</include>REAL_32</class>
			<comment>--</comment><comment> Amount text is rotated counter-clockwise from horizontal plane in radians.</comment>

	<anchor>f_set_angle</anchor><feature><location>../implementation_gtk/ev_label_imp.xml#f_set_angle</location>set_angle</feature> <symbol>(</symbol><local>a_angle</local><symbol>:</symbol> <class><include>False</include>REAL_32</class><symbol>)</symbol>
		<keyword>do</keyword>
			<symbol>{</symbol><class><location>../implementation_gtk/gtk2.xml</location>GTK2</class><symbol>}</symbol><dot>.</dot><feature><location>../implementation_gtk/gtk2.xml#f_gtk_label_set_angle</location>gtk_label_set_angle</feature> <symbol>(</symbol><feature><location>../implementation_gtk/ev_textable_imp.xml#f_text_label</location>text_label</feature><symbol>,</symbol> <local>a_angle</local> <symbol>/</symbol> <symbol>{</symbol><class><include>False</include>REAL_32</class><symbol>}</symbol> <number>3.14</number> <symbol>*</symbol> <symbol>{</symbol><class><include>False</include>REAL_32</class><symbol>}</symbol> <number>180.0</number><symbol>)</symbol>
			<feature><location>../implementation_gtk/ev_label_imp.xml#f_angle</location>angle</feature> <symbol>:=</symbol> <local>a_angle</local>
		<keyword>end</keyword>
	
<keyword>feature</keyword> <comment>--</comment><comment> Status Setting</comment>

	<anchor>f_align_text_top</anchor><feature><location>../implementation_gtk/ev_label_imp.xml#f_align_text_top</location>align_text_top</feature>
			<comment>--</comment><comment> Set vertical text alignment of current label to top.</comment>
		<keyword>do</keyword>
		<keyword>end</keyword>

	<anchor>f_align_text_vertical_center</anchor><feature><location>../implementation_gtk/ev_label_imp.xml#f_align_text_vertical_center</location>align_text_vertical_center</feature>
			<comment>--</comment><comment> Set text alignment of current label to be in the center vertically.</comment>
		<keyword>do</keyword>
		<keyword>end</keyword>

	<anchor>f_align_text_bottom</anchor><feature><location>../implementation_gtk/ev_label_imp.xml#f_align_text_bottom</location>align_text_bottom</feature>
			<comment>--</comment><comment> Set vertical text alignment of current label to bottom.</comment>
		<keyword>do</keyword>
		<keyword>end</keyword>
	
<keyword>feature</keyword> <symbol>{</symbol>NONE<symbol>}</symbol> <comment>--</comment><comment> Implementation</comment>

	<anchor>f_needs_event_box</anchor><feature><location>../implementation_gtk/ev_label_imp.xml#f_needs_event_box</location>Needs_event_box</feature><symbol>:</symbol> <class><include>False</include>BOOLEAN</class> <symbol>=</symbol> <keyword>True</keyword>
			<comment>--</comment><comment> Does </comment><quoted>a_widget</quoted><comment> need an event box?</comment>
	
<keyword>feature</keyword> <symbol>{</symbol><class><location>../interface/ev_any.xml</location>EV_ANY</class><symbol>,</symbol> <class><location>../implementation_interface/ev_any_i.xml</location>EV_ANY_I</class><symbol>}</symbol> <comment>--</comment><comment> Implementation</comment>

	<anchor>f_interface</anchor><feature><location>../implementation_gtk/ev_label_imp.xml#f_interface</location>interface</feature><symbol>:</symbol> <keyword>detachable</keyword> <class><location>../interface/ev_label.xml</location>EV_LABEL</class>
		<keyword>note</keyword>
			option: stable
		<keyword>attribute</keyword>
		<keyword>end</keyword>
	
<keyword>note</keyword>
	<indexing_tag>copyright</indexing_tag><symbol>:</symbol> <string>&quot;Copyright (c) 1984-2017, Eiffel Software and others&quot;</string>
	<indexing_tag>license</indexing_tag><symbol>:</symbol> <string>&quot;Eiffel Forum License v2 (see </string><string><location>http://www.eiffel.com/licensing/forum.txt</location>http://www.eiffel.com/licensing/forum.txt</string><string>)&quot;</string>
	<indexing_tag>source</indexing_tag><symbol>:</symbol> <string>&quot;</string><string>[</string>
		<string>Eiffel Software</string>
		<string>5949 Hollister Ave., Goleta, CA 93117 USA</string>
		<string>Telephone 805-685-1006, Fax 805-685-6869</string>
		<string>Website </string><string><location>http://www.eiffel.com</location>http://www.eiffel.com</string>
		<string>Customer support </string><string><location>http://support.eiffel.com</location>http://support.eiffel.com</string>
	<string>]</string><string>&quot;</string>

<keyword>end</keyword> <comment>--</comment> <comment>class </comment><class><location>../implementation_gtk/ev_label_imp.xml</location>EV_LABEL_IMP</class></system>

